<?xml version="1.0" encoding="utf-8"?><response>
<statusCode>200</statusCode>
<statusText>Ok</statusText>
<data>
<testId>170312_10_7e85ef385f3bcf0cf694bd204283305d</testId>
<summary>http://104.198.155.24/results.php?test=170312_10_7e85ef385f3bcf0cf694bd204283305d</summary>
<testUrl>http://amp.timeinc.net/time/4677757/supreme-mta-fare-cards-subway-nyc/</testUrl>
<location>Alex3:Chrome</location>
<from>Alex - &lt;b&gt;Chrome&lt;/b&gt; - &lt;b&gt;custom&lt;/b&gt;</from>
<connectivity>custom</connectivity>
<bwDown>1500</bwDown>
<bwUp>384</bwUp>
<latency>50</latency>
<plr>0</plr>
<mobile>0</mobile>
<completed>Sun, 12 Mar 2017 10:46:21 +0000</completed>
<tester>WIN-V9F8885QKK2-165.124.182.230</tester>
<testerDNS>172.16.192.2</testerDNS>
<runs>2</runs>
<successfulFVRuns>2</successfulFVRuns>
<average>
<firstView>
<loadTime>16514</loadTime>
<TTFB>1318</TTFB>
<bytesOut>56997</bytesOut>
<bytesOutDoc>55526</bytesOutDoc>
<bytesIn>1101265</bytesIn>
<bytesInDoc>1094852</bytesInDoc>
<connections>29</connections>
<requests>65</requests>
<requestsFull>65</requestsFull>
<requestsDoc>64</requestsDoc>
<responses_200>58</responses_200>
<responses_404>1</responses_404>
<responses_other>4</responses_other>
<result>99999</result>
<render>2017</render>
<fullyLoaded>16617</fullyLoaded>
<cached>0</cached>
<docTime>16514</docTime>
<domTime>0</domTime>
<score_cache>43</score_cache>
<score_cdn>91</score_cdn>
<score_gzip>58</score_gzip>
<score_cookies>-1</score_cookies>
<score_keep-alive>99</score_keep-alive>
<score_minify>-1</score_minify>
<score_combine>100</score_combine>
<score_compress>63</score_compress>
<score_etags>-1</score_etags>
<gzip_total>70400</gzip_total>
<gzip_savings>28890</gzip_savings>
<minify_total>0</minify_total>
<minify_savings>0</minify_savings>
<image_total>151084</image_total>
<image_savings>54729</image_savings>
<optimization_checked>1</optimization_checked>
<aft>0</aft>
<domElements>172</domElements>
<pageSpeedVersion>2</pageSpeedVersion>
<titleTime>1694</titleTime>
<loadEventStart>15898</loadEventStart>
<loadEventEnd>15901</loadEventEnd>
<domContentLoadedEventStart>1639</domContentLoadedEventStart>
<domContentLoadedEventEnd>1639</domContentLoadedEventEnd>
<lastVisualChange>16762</lastVisualChange>
<server_count>8</server_count>
<server_rtt>58</server_rtt>
<adult_site>0</adult_site>
<fixed_viewport>1</fixed_viewport>
<score_progressive_jpeg>0</score_progressive_jpeg>
<firstPaint>5317</firstPaint>
<docCPUms>14875</docCPUms>
<fullyLoadedCPUms>16076</fullyLoadedCPUms>
<docCPUpct>89</docCPUpct>
<fullyLoadedCPUpct>84</fullyLoadedCPUpct>
<isResponsive>-1</isResponsive>
<date>1489315538</date>
<userTime.is>4917</userTime.is>
<userTime.e_is>5030</userTime.e_is>
<userTime.ofv>5124</userTime.ofv>
<userTime.mbv>5195</userTime.mbv>
<userTime.pc>11259</userTime.pc>
<userTime.ol>15899</userTime.ol>
<userTime>15899</userTime>
<SpeedIndex>8341</SpeedIndex>
<visualComplete>8900</visualComplete>
<chromeUserTiming.fetchStart>1</chromeUserTiming.fetchStart>
<chromeUserTiming.unloadEventStart>1330</chromeUserTiming.unloadEventStart>
<chromeUserTiming.unloadEventEnd>1330</chromeUserTiming.unloadEventEnd>
<chromeUserTiming.responseEnd>1598</chromeUserTiming.responseEnd>
<chromeUserTiming.firstMeaningfulPaint>5318</chromeUserTiming.firstMeaningfulPaint>
<chromeUserTiming.loadEventStart>15898</chromeUserTiming.loadEventStart>
<chromeUserTiming.loadEventEnd>15901</chromeUserTiming.loadEventEnd>
<run>2</run>
<effectiveBps>72565</effectiveBps>
<effectiveBpsDoc>72595</effectiveBpsDoc>
<avgRun>1</avgRun>
</firstView>
</average>
<standardDeviation>
<firstView>
<loadTime>423</loadTime>
<TTFB>1087</TTFB>
<bytesOut>19493</bytesOut>
<bytesOutDoc>18022</bytesOutDoc>
<bytesIn>32905</bytesIn>
<bytesInDoc>26493</bytesInDoc>
<connections>10</connections>
<requests>8</requests>
<requestsFull>8</requestsFull>
<requestsDoc>8</requestsDoc>
<responses_200>7</responses_200>
<responses_404>0</responses_404>
<responses_other>2</responses_other>
<result>0</result>
<render>556</render>
<fullyLoaded>526</fullyLoaded>
<cached>0</cached>
<docTime>423</docTime>
<domTime>0</domTime>
<score_cache>1</score_cache>
<score_cdn>9</score_cdn>
<score_gzip>1</score_gzip>
<score_cookies>0</score_cookies>
<score_keep-alive>1</score_keep-alive>
<score_minify>0</score_minify>
<score_combine>0</score_combine>
<score_compress>0</score_compress>
<score_etags>0</score_etags>
<gzip_total>1703</gzip_total>
<gzip_savings>0</gzip_savings>
<minify_total>0</minify_total>
<minify_savings>0</minify_savings>
<image_total>0</image_total>
<image_savings>0</image_savings>
<optimization_checked>0</optimization_checked>
<aft>0</aft>
<domElements>0</domElements>
<pageSpeedVersion>0</pageSpeedVersion>
<titleTime>1153</titleTime>
<loadEventStart>625</loadEventStart>
<loadEventEnd>628</loadEventEnd>
<domContentLoadedEventStart>1053</domContentLoadedEventStart>
<domContentLoadedEventEnd>1053</domContentLoadedEventEnd>
<lastVisualChange>677</lastVisualChange>
<server_count>0</server_count>
<server_rtt>1</server_rtt>
<adult_site>0</adult_site>
<fixed_viewport>0</fixed_viewport>
<score_progressive_jpeg>0</score_progressive_jpeg>
<firstPaint>551</firstPaint>
<docCPUms>1333</docCPUms>
<fullyLoadedCPUms>1583</fullyLoadedCPUms>
<docCPUpct>5</docCPUpct>
<fullyLoadedCPUpct>5</fullyLoadedCPUpct>
<isResponsive>0</isResponsive>
<date>17</date>
<userTime.is>577</userTime.is>
<userTime.e_is>590</userTime.e_is>
<userTime.ofv>564</userTime.ofv>
<userTime.mbv>537</userTime.mbv>
<userTime.pc>2740</userTime.pc>
<userTime.ol>624</userTime.ol>
<userTime>624</userTime>
<SpeedIndex>1374</SpeedIndex>
<visualComplete>1800</visualComplete>
<chromeUserTiming.fetchStart>0</chromeUserTiming.fetchStart>
<chromeUserTiming.unloadEventStart>1076</chromeUserTiming.unloadEventStart>
<chromeUserTiming.unloadEventEnd>1076</chromeUserTiming.unloadEventEnd>
<chromeUserTiming.responseEnd>1082</chromeUserTiming.responseEnd>
<chromeUserTiming.firstMeaningfulPaint>551</chromeUserTiming.firstMeaningfulPaint>
<chromeUserTiming.loadEventStart>625</chromeUserTiming.loadEventStart>
<chromeUserTiming.loadEventEnd>628</chromeUserTiming.loadEventEnd>
<run>0</run>
<effectiveBps>5502</effectiveBps>
<effectiveBpsDoc>5472</effectiveBpsDoc>
<avgRun/>
</firstView>
</standardDeviation>
<median>
<firstView>
<run>1</run>
<tester>WIN-V9F8885QKK2-165.124.182.230</tester>
<URL>http://amp.timeinc.net/time/4677757/supreme-mta-fare-cards-subway-nyc/</URL>
<loadTime>16090</loadTime>
<TTFB>2405</TTFB>
<bytesOut>37504</bytesOut>
<bytesOutDoc>37504</bytesOutDoc>
<bytesIn>1068359</bytesIn>
<bytesInDoc>1068359</bytesInDoc>
<connections>18</connections>
<requests>56</requests>
<requestsFull>56</requestsFull>
<requestsDoc>56</requestsDoc>
<responses_200>51</responses_200>
<responses_404>1</responses_404>
<responses_other>2</responses_other>
<result>99999</result>
<render>2573</render>
<fullyLoaded>16090</fullyLoaded>
<cached>0</cached>
<docTime>16090</docTime>
<domTime>0</domTime>
<score_cache>41</score_cache>
<score_cdn>100</score_cdn>
<score_gzip>57</score_gzip>
<score_cookies>-1</score_cookies>
<score_keep-alive>100</score_keep-alive>
<score_minify>-1</score_minify>
<score_combine>100</score_combine>
<score_compress>63</score_compress>
<score_etags>-1</score_etags>
<gzip_total>68696</gzip_total>
<gzip_savings>28890</gzip_savings>
<minify_total>0</minify_total>
<minify_savings>0</minify_savings>
<image_total>151084</image_total>
<image_savings>54729</image_savings>
<optimization_checked>1</optimization_checked>
<aft>0</aft>
<domElements>172</domElements>
<pageSpeedVersion>1.9</pageSpeedVersion>
<title>Here&amp;rsquo;s Why These Desirable Fashion Subway Cards Are Selling on Ebay for $100</title>
<titleTime>2847</titleTime>
<loadEventStart>15273</loadEventStart>
<loadEventEnd>15273</loadEventEnd>
<domContentLoadedEventStart>2692</domContentLoadedEventStart>
<domContentLoadedEventEnd>2692</domContentLoadedEventEnd>
<lastVisualChange>16085</lastVisualChange>
<browser_name>Google Chrome</browser_name>
<browser_version>56.0.2924.87</browser_version>
<server_count>8</server_count>
<server_rtt>56</server_rtt>
<base_page_cdn>Amazon CloudFront</base_page_cdn>
<adult_site>0</adult_site>
<fixed_viewport>1</fixed_viewport>
<score_progressive_jpeg>0</score_progressive_jpeg>
<firstPaint>5868</firstPaint>
<docCPUms>13540.887</docCPUms>
<fullyLoadedCPUms>14492.493</fullyLoadedCPUms>
<docCPUpct>83</docCPUpct>
<fullyLoadedCPUpct>79</fullyLoadedCPUpct>
<isResponsive>-1</isResponsive>
<date>1489315521</date>
<userTime.is>5494</userTime.is>
<userTimes>
<is>5494</is>
<e_is>5620</e_is>
<ofv>5688</ofv>
<mbv>5732</mbv>
<pc>13999</pc>
<ol>15274</ol>
</userTimes>
<userTime.e_is>5620</userTime.e_is>
<userTime.ofv>5688</userTime.ofv>
<userTime.mbv>5732</userTime.mbv>
<userTime.pc>13999</userTime.pc>
<userTime.ol>15274</userTime.ol>
<userTime>15274</userTime>
<SpeedIndex>9715</SpeedIndex>
<visualComplete>10700</visualComplete>
<chromeUserTiming>
<value>
<name>fetchStart</name>
<time>1</time>
</value>
<value>
<name>unloadEventStart</name>
<time>2406</time>
</value>
<value>
<name>unloadEventEnd</name>
<time>2406</time>
</value>
<value>
<name>responseEnd</name>
<time>2680</time>
</value>
<value>
<name>firstMeaningfulPaint</name>
<time>5869</time>
</value>
<value>
<name>loadEventStart</name>
<time>15273</time>
</value>
<value>
<name>loadEventEnd</name>
<time>15273</time>
</value>
</chromeUserTiming>
<chromeUserTiming.fetchStart>1</chromeUserTiming.fetchStart>
<chromeUserTiming.unloadEventStart>2406</chromeUserTiming.unloadEventStart>
<chromeUserTiming.unloadEventEnd>2406</chromeUserTiming.unloadEventEnd>
<chromeUserTiming.responseEnd>2680</chromeUserTiming.responseEnd>
<chromeUserTiming.firstMeaningfulPaint>5869</chromeUserTiming.firstMeaningfulPaint>
<chromeUserTiming.loadEventStart>15273</chromeUserTiming.loadEventStart>
<chromeUserTiming.loadEventEnd>15273</chromeUserTiming.loadEventEnd>
<run>1</run>
<effectiveBps>78067</effectiveBps>
<effectiveBpsDoc>78067</effectiveBpsDoc>
<consoleLog>
<entry>
<source>console-api</source>
<level>info</level>
<message/>
<url>https://cdn.ampproject.org/v0.js</url>
<line>384</line>
</entry>
</consoleLog>
</firstView>
</median>
<run>
<id>1</id>
<firstView>
<tester>WIN-V9F8885QKK2-165.124.182.230</tester>
<results>
<URL>http://amp.timeinc.net/time/4677757/supreme-mta-fare-cards-subway-nyc/</URL>
<loadTime>16090</loadTime>
<TTFB>2405</TTFB>
<bytesOut>37504</bytesOut>
<bytesOutDoc>37504</bytesOutDoc>
<bytesIn>1068359</bytesIn>
<bytesInDoc>1068359</bytesInDoc>
<connections>18</connections>
<requests>56</requests>
<requestsFull>56</requestsFull>
<requestsDoc>56</requestsDoc>
<responses_200>51</responses_200>
<responses_404>1</responses_404>
<responses_other>2</responses_other>
<result>99999</result>
<render>2573</render>
<fullyLoaded>16090</fullyLoaded>
<cached>0</cached>
<docTime>16090</docTime>
<domTime>0</domTime>
<score_cache>41</score_cache>
<score_cdn>100</score_cdn>
<score_gzip>57</score_gzip>
<score_cookies>-1</score_cookies>
<score_keep-alive>100</score_keep-alive>
<score_minify>-1</score_minify>
<score_combine>100</score_combine>
<score_compress>63</score_compress>
<score_etags>-1</score_etags>
<gzip_total>68696</gzip_total>
<gzip_savings>28890</gzip_savings>
<minify_total>0</minify_total>
<minify_savings>0</minify_savings>
<image_total>151084</image_total>
<image_savings>54729</image_savings>
<optimization_checked>1</optimization_checked>
<aft>0</aft>
<domElements>172</domElements>
<pageSpeedVersion>1.9</pageSpeedVersion>
<title>Here&amp;rsquo;s Why These Desirable Fashion Subway Cards Are Selling on Ebay for $100</title>
<titleTime>2847</titleTime>
<loadEventStart>15273</loadEventStart>
<loadEventEnd>15273</loadEventEnd>
<domContentLoadedEventStart>2692</domContentLoadedEventStart>
<domContentLoadedEventEnd>2692</domContentLoadedEventEnd>
<lastVisualChange>16085</lastVisualChange>
<browser_name>Google Chrome</browser_name>
<browser_version>56.0.2924.87</browser_version>
<server_count>8</server_count>
<server_rtt>56</server_rtt>
<base_page_cdn>Amazon CloudFront</base_page_cdn>
<adult_site>0</adult_site>
<fixed_viewport>1</fixed_viewport>
<score_progressive_jpeg>0</score_progressive_jpeg>
<firstPaint>5868</firstPaint>
<docCPUms>13540.887</docCPUms>
<fullyLoadedCPUms>14492.493</fullyLoadedCPUms>
<docCPUpct>83</docCPUpct>
<fullyLoadedCPUpct>79</fullyLoadedCPUpct>
<isResponsive>-1</isResponsive>
<date>1489315521</date>
<userTime.is>5494</userTime.is>
<userTimes>
<is>5494</is>
<e_is>5620</e_is>
<ofv>5688</ofv>
<mbv>5732</mbv>
<pc>13999</pc>
<ol>15274</ol>
</userTimes>
<userTime.e_is>5620</userTime.e_is>
<userTime.ofv>5688</userTime.ofv>
<userTime.mbv>5732</userTime.mbv>
<userTime.pc>13999</userTime.pc>
<userTime.ol>15274</userTime.ol>
<userTime>15274</userTime>
<SpeedIndex>9715</SpeedIndex>
<visualComplete>10700</visualComplete>
<chromeUserTiming>
<value>
<name>fetchStart</name>
<time>1</time>
</value>
<value>
<name>unloadEventStart</name>
<time>2406</time>
</value>
<value>
<name>unloadEventEnd</name>
<time>2406</time>
</value>
<value>
<name>responseEnd</name>
<time>2680</time>
</value>
<value>
<name>firstMeaningfulPaint</name>
<time>5869</time>
</value>
<value>
<name>loadEventStart</name>
<time>15273</time>
</value>
<value>
<name>loadEventEnd</name>
<time>15273</time>
</value>
</chromeUserTiming>
<chromeUserTiming.fetchStart>1</chromeUserTiming.fetchStart>
<chromeUserTiming.unloadEventStart>2406</chromeUserTiming.unloadEventStart>
<chromeUserTiming.unloadEventEnd>2406</chromeUserTiming.unloadEventEnd>
<chromeUserTiming.responseEnd>2680</chromeUserTiming.responseEnd>
<chromeUserTiming.firstMeaningfulPaint>5869</chromeUserTiming.firstMeaningfulPaint>
<chromeUserTiming.loadEventStart>15273</chromeUserTiming.loadEventStart>
<chromeUserTiming.loadEventEnd>15273</chromeUserTiming.loadEventEnd>
<run>1</run>
<effectiveBps>78067</effectiveBps>
<effectiveBpsDoc>78067</effectiveBpsDoc>
</results>
<pages>
<details>http://104.198.155.24/details.php?test=170312_10_7e85ef385f3bcf0cf694bd204283305d&amp;run=1</details>
<checklist>http://104.198.155.24/performance_optimization.php?test=170312_10_7e85ef385f3bcf0cf694bd204283305d&amp;run=1</checklist>
<breakdown>http://104.198.155.24/breakdown.php?test=170312_10_7e85ef385f3bcf0cf694bd204283305d&amp;run=1</breakdown>
<domains>http://104.198.155.24/domains.php?test=170312_10_7e85ef385f3bcf0cf694bd204283305d&amp;run=1</domains>
<screenShot>http://104.198.155.24/screen_shot.php?test=170312_10_7e85ef385f3bcf0cf694bd204283305d&amp;run=1</screenShot>
</pages>
<thumbnails>
<waterfall>http://104.198.155.24/result/170312_10_7e85ef385f3bcf0cf694bd204283305d/1_waterfall_thumb.png</waterfall>
<checklist>http://104.198.155.24/result/170312_10_7e85ef385f3bcf0cf694bd204283305d/1_optimization_thumb.png</checklist>
<screenShot>http://104.198.155.24/result/170312_10_7e85ef385f3bcf0cf694bd204283305d/1_screen_thumb.jpg</screenShot>
</thumbnails>
<images>
<waterfall>http://104.198.155.24/results/17/03/12/10/7e85ef385f3bcf0cf694bd204283305d/1_waterfall.png</waterfall>
<connectionView>http://104.198.155.24/results/17/03/12/10/7e85ef385f3bcf0cf694bd204283305d/1_connection.png</connectionView>
<checklist>http://104.198.155.24/results/17/03/12/10/7e85ef385f3bcf0cf694bd204283305d/1_optimization.png</checklist>
<screenShot>http://104.198.155.24/getfile.php?test=170312_10_7e85ef385f3bcf0cf694bd204283305d&amp;file=1_screen.jpg</screenShot>
</images>
<rawData><headers>http://104.198.155.24/results/17/03/12/10/7e85ef385f3bcf0cf694bd204283305d/1_report.txt</headers>
<pageData>http://104.198.155.24/results/17/03/12/10/7e85ef385f3bcf0cf694bd204283305d/1_IEWPG.txt</pageData>
<requestsData>http://104.198.155.24/results/17/03/12/10/7e85ef385f3bcf0cf694bd204283305d/1_IEWTR.txt</requestsData>
<utilization>http://104.198.155.24/results/17/03/12/10/7e85ef385f3bcf0cf694bd204283305d/1_progress.csv</utilization>
</rawData>
<videoFrames>
<frame>
<time>0</time>
<image>http://104.198.155.24/getfile.php?test=170312_10_7e85ef385f3bcf0cf694bd204283305d&amp;video=video_1&amp;file=frame_0000.jpg</image>
<VisuallyComplete>0</VisuallyComplete>
</frame>
<frame>
<time>2600</time>
<image>http://104.198.155.24/getfile.php?test=170312_10_7e85ef385f3bcf0cf694bd204283305d&amp;video=video_1&amp;file=frame_0026.jpg</image>
<VisuallyComplete>0</VisuallyComplete>
</frame>
<frame>
<time>5400</time>
<image>http://104.198.155.24/getfile.php?test=170312_10_7e85ef385f3bcf0cf694bd204283305d&amp;video=video_1&amp;file=frame_0054.jpg</image>
<VisuallyComplete>0</VisuallyComplete>
</frame>
<frame>
<time>5600</time>
<image>http://104.198.155.24/getfile.php?test=170312_10_7e85ef385f3bcf0cf694bd204283305d&amp;video=video_1&amp;file=frame_0056.jpg</image>
<VisuallyComplete>0</VisuallyComplete>
</frame>
<frame>
<time>6600</time>
<image>http://104.198.155.24/getfile.php?test=170312_10_7e85ef385f3bcf0cf694bd204283305d&amp;video=video_1&amp;file=frame_0066.jpg</image>
<VisuallyComplete>0</VisuallyComplete>
</frame>
<frame>
<time>6900</time>
<image>http://104.198.155.24/getfile.php?test=170312_10_7e85ef385f3bcf0cf694bd204283305d&amp;video=video_1&amp;file=frame_0069.jpg</image>
<VisuallyComplete>7</VisuallyComplete>
</frame>
<frame>
<time>8000</time>
<image>http://104.198.155.24/getfile.php?test=170312_10_7e85ef385f3bcf0cf694bd204283305d&amp;video=video_1&amp;file=frame_0080.jpg</image>
<VisuallyComplete>7</VisuallyComplete>
</frame>
<frame>
<time>8100</time>
<image>http://104.198.155.24/getfile.php?test=170312_10_7e85ef385f3bcf0cf694bd204283305d&amp;video=video_1&amp;file=frame_0081.jpg</image>
<VisuallyComplete>6</VisuallyComplete>
</frame>
<frame>
<time>8900</time>
<image>http://104.198.155.24/getfile.php?test=170312_10_7e85ef385f3bcf0cf694bd204283305d&amp;video=video_1&amp;file=frame_0089.jpg</image>
<VisuallyComplete>13</VisuallyComplete>
</frame>
<frame>
<time>9800</time>
<image>http://104.198.155.24/getfile.php?test=170312_10_7e85ef385f3bcf0cf694bd204283305d&amp;video=video_1&amp;file=frame_0098.jpg</image>
<VisuallyComplete>85</VisuallyComplete>
</frame>
<frame>
<time>10700</time>
<image>http://104.198.155.24/getfile.php?test=170312_10_7e85ef385f3bcf0cf694bd204283305d&amp;video=video_1&amp;file=frame_0107.jpg</image>
<VisuallyComplete>100</VisuallyComplete>
</frame>
<frame>
<time>12800</time>
<image>http://104.198.155.24/getfile.php?test=170312_10_7e85ef385f3bcf0cf694bd204283305d&amp;video=video_1&amp;file=frame_0128.jpg</image>
<VisuallyComplete>99</VisuallyComplete>
</frame>
<frame>
<time>15000</time>
<image>http://104.198.155.24/getfile.php?test=170312_10_7e85ef385f3bcf0cf694bd204283305d&amp;video=video_1&amp;file=frame_0150.jpg</image>
<VisuallyComplete>100</VisuallyComplete>
</frame>
<frame>
<time>15100</time>
<image>http://104.198.155.24/getfile.php?test=170312_10_7e85ef385f3bcf0cf694bd204283305d&amp;video=video_1&amp;file=frame_0151.jpg</image>
<VisuallyComplete>100</VisuallyComplete>
</frame>
<frame>
<time>15400</time>
<image>http://104.198.155.24/getfile.php?test=170312_10_7e85ef385f3bcf0cf694bd204283305d&amp;video=video_1&amp;file=frame_0154.jpg</image>
<VisuallyComplete>99</VisuallyComplete>
</frame>
<frame>
<time>15900</time>
<image>http://104.198.155.24/getfile.php?test=170312_10_7e85ef385f3bcf0cf694bd204283305d&amp;video=video_1&amp;file=frame_0159.jpg</image>
<VisuallyComplete>99</VisuallyComplete>
</frame>
<frame>
<time>16100</time>
<image>http://104.198.155.24/getfile.php?test=170312_10_7e85ef385f3bcf0cf694bd204283305d&amp;video=video_1&amp;file=frame_0161.jpg</image>
<VisuallyComplete>100</VisuallyComplete>
</frame>
</videoFrames>
<consoleLog>
<entry>
<source>console-api</source>
<level>info</level>
<message/>
<url>https://cdn.ampproject.org/v0.js</url>
<line>384</line>
</entry>
</consoleLog>
</firstView>
</run>
<run>
<id>2</id>
<firstView>
<tester>WIN-V9F8885QKK2-165.124.182.230</tester>
<results>
<URL>http://amp.timeinc.net/time/4677757/supreme-mta-fare-cards-subway-nyc/</URL>
<loadTime>16937</loadTime>
<TTFB>231</TTFB>
<bytesOut>76490</bytesOut>
<bytesOutDoc>73548</bytesOutDoc>
<bytesIn>1134170</bytesIn>
<bytesInDoc>1121345</bytesInDoc>
<connections>39</connections>
<requests>73</requests>
<requestsFull>73</requestsFull>
<requestsDoc>72</requestsDoc>
<responses_200>65</responses_200>
<responses_404>1</responses_404>
<responses_other>6</responses_other>
<result>99999</result>
<render>1460</render>
<fullyLoaded>17143</fullyLoaded>
<cached>0</cached>
<docTime>16937</docTime>
<domTime>0</domTime>
<score_cache>44</score_cache>
<score_cdn>82</score_cdn>
<score_gzip>59</score_gzip>
<score_cookies>-1</score_cookies>
<score_keep-alive>98</score_keep-alive>
<score_minify>-1</score_minify>
<score_combine>100</score_combine>
<score_compress>63</score_compress>
<score_etags>-1</score_etags>
<gzip_total>72103</gzip_total>
<gzip_savings>28890</gzip_savings>
<minify_total>0</minify_total>
<minify_savings>0</minify_savings>
<image_total>151084</image_total>
<image_savings>54729</image_savings>
<optimization_checked>1</optimization_checked>
<aft>0</aft>
<domElements>172</domElements>
<pageSpeedVersion>1.9</pageSpeedVersion>
<title>Here&amp;rsquo;s Why These Desirable Fashion Subway Cards Are Selling on Ebay for $100</title>
<titleTime>541</titleTime>
<loadEventStart>16523</loadEventStart>
<loadEventEnd>16529</loadEventEnd>
<domContentLoadedEventStart>585</domContentLoadedEventStart>
<domContentLoadedEventEnd>585</domContentLoadedEventEnd>
<lastVisualChange>17439</lastVisualChange>
<browser_name>Google Chrome</browser_name>
<browser_version>56.0.2924.87</browser_version>
<server_count>8</server_count>
<server_rtt>59</server_rtt>
<base_page_cdn>Amazon CloudFront</base_page_cdn>
<adult_site>0</adult_site>
<fixed_viewport>1</fixed_viewport>
<score_progressive_jpeg>0</score_progressive_jpeg>
<firstPaint>4766</firstPaint>
<docCPUms>16208.504</docCPUms>
<fullyLoadedCPUms>17659.313</fullyLoadedCPUms>
<docCPUpct>94</docCPUpct>
<fullyLoadedCPUpct>89</fullyLoadedCPUpct>
<isResponsive>-1</isResponsive>
<date>1489315555</date>
<userTime.is>4339</userTime.is>
<userTimes>
<is>4339</is>
<e_is>4440</e_is>
<ofv>4559</ofv>
<mbv>4658</mbv>
<pc>8519</pc>
<ol>16523</ol>
</userTimes>
<userTime.e_is>4440</userTime.e_is>
<userTime.ofv>4559</userTime.ofv>
<userTime.mbv>4658</userTime.mbv>
<userTime.pc>8519</userTime.pc>
<userTime.ol>16523</userTime.ol>
<userTime>16523</userTime>
<SpeedIndex>6967</SpeedIndex>
<visualComplete>7100</visualComplete>
<chromeUserTiming>
<value>
<name>fetchStart</name>
<time>1</time>
</value>
<value>
<name>unloadEventStart</name>
<time>254</time>
</value>
<value>
<name>unloadEventEnd</name>
<time>254</time>
</value>
<value>
<name>responseEnd</name>
<time>516</time>
</value>
<value>
<name>firstMeaningfulPaint</name>
<time>4766</time>
</value>
<value>
<name>loadEventStart</name>
<time>16523</time>
</value>
<value>
<name>loadEventEnd</name>
<time>16529</time>
</value>
</chromeUserTiming>
<chromeUserTiming.fetchStart>1</chromeUserTiming.fetchStart>
<chromeUserTiming.unloadEventStart>254</chromeUserTiming.unloadEventStart>
<chromeUserTiming.unloadEventEnd>254</chromeUserTiming.unloadEventEnd>
<chromeUserTiming.responseEnd>516</chromeUserTiming.responseEnd>
<chromeUserTiming.firstMeaningfulPaint>4766</chromeUserTiming.firstMeaningfulPaint>
<chromeUserTiming.loadEventStart>16523</chromeUserTiming.loadEventStart>
<chromeUserTiming.loadEventEnd>16529</chromeUserTiming.loadEventEnd>
<run>2</run>
<effectiveBps>67063</effectiveBps>
<effectiveBpsDoc>67122</effectiveBpsDoc>
</results>
<pages>
<details>http://104.198.155.24/details.php?test=170312_10_7e85ef385f3bcf0cf694bd204283305d&amp;run=2</details>
<checklist>http://104.198.155.24/performance_optimization.php?test=170312_10_7e85ef385f3bcf0cf694bd204283305d&amp;run=2</checklist>
<breakdown>http://104.198.155.24/breakdown.php?test=170312_10_7e85ef385f3bcf0cf694bd204283305d&amp;run=2</breakdown>
<domains>http://104.198.155.24/domains.php?test=170312_10_7e85ef385f3bcf0cf694bd204283305d&amp;run=2</domains>
<screenShot>http://104.198.155.24/screen_shot.php?test=170312_10_7e85ef385f3bcf0cf694bd204283305d&amp;run=2</screenShot>
</pages>
<thumbnails>
<waterfall>http://104.198.155.24/result/170312_10_7e85ef385f3bcf0cf694bd204283305d/2_waterfall_thumb.png</waterfall>
<checklist>http://104.198.155.24/result/170312_10_7e85ef385f3bcf0cf694bd204283305d/2_optimization_thumb.png</checklist>
<screenShot>http://104.198.155.24/result/170312_10_7e85ef385f3bcf0cf694bd204283305d/2_screen_thumb.jpg</screenShot>
</thumbnails>
<images>
<waterfall>http://104.198.155.24/results/17/03/12/10/7e85ef385f3bcf0cf694bd204283305d/2_waterfall.png</waterfall>
<connectionView>http://104.198.155.24/results/17/03/12/10/7e85ef385f3bcf0cf694bd204283305d/2_connection.png</connectionView>
<checklist>http://104.198.155.24/results/17/03/12/10/7e85ef385f3bcf0cf694bd204283305d/2_optimization.png</checklist>
<screenShot>http://104.198.155.24/getfile.php?test=170312_10_7e85ef385f3bcf0cf694bd204283305d&amp;file=2_screen.jpg</screenShot>
</images>
<rawData><headers>http://104.198.155.24/results/17/03/12/10/7e85ef385f3bcf0cf694bd204283305d/2_report.txt</headers>
<pageData>http://104.198.155.24/results/17/03/12/10/7e85ef385f3bcf0cf694bd204283305d/2_IEWPG.txt</pageData>
<requestsData>http://104.198.155.24/results/17/03/12/10/7e85ef385f3bcf0cf694bd204283305d/2_IEWTR.txt</requestsData>
<utilization>http://104.198.155.24/results/17/03/12/10/7e85ef385f3bcf0cf694bd204283305d/2_progress.csv</utilization>
</rawData>
<videoFrames>
<frame>
<time>0</time>
<image>http://104.198.155.24/getfile.php?test=170312_10_7e85ef385f3bcf0cf694bd204283305d&amp;video=video_2&amp;file=frame_0000.jpg</image>
<VisuallyComplete>0</VisuallyComplete>
</frame>
<frame>
<time>1500</time>
<image>http://104.198.155.24/getfile.php?test=170312_10_7e85ef385f3bcf0cf694bd204283305d&amp;video=video_2&amp;file=frame_0015.jpg</image>
<VisuallyComplete>0</VisuallyComplete>
</frame>
<frame>
<time>2900</time>
<image>http://104.198.155.24/getfile.php?test=170312_10_7e85ef385f3bcf0cf694bd204283305d&amp;video=video_2&amp;file=frame_0029.jpg</image>
<VisuallyComplete>0</VisuallyComplete>
</frame>
<frame>
<time>3100</time>
<image>http://104.198.155.24/getfile.php?test=170312_10_7e85ef385f3bcf0cf694bd204283305d&amp;video=video_2&amp;file=frame_0031.jpg</image>
<VisuallyComplete>0</VisuallyComplete>
</frame>
<frame>
<time>5000</time>
<image>http://104.198.155.24/getfile.php?test=170312_10_7e85ef385f3bcf0cf694bd204283305d&amp;video=video_2&amp;file=frame_0050.jpg</image>
<VisuallyComplete>0</VisuallyComplete>
</frame>
<frame>
<time>5300</time>
<image>http://104.198.155.24/getfile.php?test=170312_10_7e85ef385f3bcf0cf694bd204283305d&amp;video=video_2&amp;file=frame_0053.jpg</image>
<VisuallyComplete>7</VisuallyComplete>
</frame>
<frame>
<time>6200</time>
<image>http://104.198.155.24/getfile.php?test=170312_10_7e85ef385f3bcf0cf694bd204283305d&amp;video=video_2&amp;file=frame_0062.jpg</image>
<VisuallyComplete>14</VisuallyComplete>
</frame>
<frame>
<time>6400</time>
<image>http://104.198.155.24/getfile.php?test=170312_10_7e85ef385f3bcf0cf694bd204283305d&amp;video=video_2&amp;file=frame_0064.jpg</image>
<VisuallyComplete>13</VisuallyComplete>
</frame>
<frame>
<time>7100</time>
<image>http://104.198.155.24/getfile.php?test=170312_10_7e85ef385f3bcf0cf694bd204283305d&amp;video=video_2&amp;file=frame_0071.jpg</image>
<VisuallyComplete>100</VisuallyComplete>
</frame>
<frame>
<time>12400</time>
<image>http://104.198.155.24/getfile.php?test=170312_10_7e85ef385f3bcf0cf694bd204283305d&amp;video=video_2&amp;file=frame_0124.jpg</image>
<VisuallyComplete>99</VisuallyComplete>
</frame>
<frame>
<time>17100</time>
<image>http://104.198.155.24/getfile.php?test=170312_10_7e85ef385f3bcf0cf694bd204283305d&amp;video=video_2&amp;file=frame_0171.jpg</image>
<VisuallyComplete>99</VisuallyComplete>
</frame>
<frame>
<time>17300</time>
<image>http://104.198.155.24/getfile.php?test=170312_10_7e85ef385f3bcf0cf694bd204283305d&amp;video=video_2&amp;file=frame_0173.jpg</image>
<VisuallyComplete>100</VisuallyComplete>
</frame>
<frame>
<time>17400</time>
<image>http://104.198.155.24/getfile.php?test=170312_10_7e85ef385f3bcf0cf694bd204283305d&amp;video=video_2&amp;file=frame_0174.jpg</image>
<VisuallyComplete>100</VisuallyComplete>
</frame>
</videoFrames>
<consoleLog>
<entry>
<source>console-api</source>
<level>info</level>
<message/>
<url>https://cdn.ampproject.org/v0.js</url>
<line>384</line>
</entry>
</consoleLog>
</firstView>
</run>
</data>
</response>