<?xml version="1.0" encoding="utf-8"?><response>
<statusCode>200</statusCode>
<statusText>Ok</statusText>
<data>
<testId>170312_CK_a6a1d62a7f6a2821f8cb6be7de39699b</testId>
<summary>http://104.198.155.24/results.php?test=170312_CK_a6a1d62a7f6a2821f8cb6be7de39699b</summary>
<testUrl>https://www.washingtonpost.com/amphtml/news/the-fix/wp/2017/02/05/how-washington-state-became-the-epicenter-of-resistance-to-trumps-agenda/</testUrl>
<location>Alex3:Chrome</location>
<from>Alex - &lt;b&gt;Chrome&lt;/b&gt; - &lt;b&gt;custom&lt;/b&gt;</from>
<connectivity>custom</connectivity>
<bwDown>1500</bwDown>
<bwUp>384</bwUp>
<latency>50</latency>
<plr>0</plr>
<mobile>0</mobile>
<completed>Sun, 12 Mar 2017 22:45:26 +0000</completed>
<tester>WIN-V9F8885QKK2-165.124.182.230</tester>
<testerDNS>172.16.192.2</testerDNS>
<runs>2</runs>
<successfulFVRuns>2</successfulFVRuns>
<average>
<firstView>
<loadTime>18048</loadTime>
<TTFB>1275</TTFB>
<bytesOut>51837</bytesOut>
<bytesOutDoc>41868</bytesOutDoc>
<bytesIn>1368398</bytesIn>
<bytesInDoc>1332672</bytesInDoc>
<connections>21</connections>
<requests>53</requests>
<requestsFull>53</requestsFull>
<requestsDoc>51</requestsDoc>
<responses_200>49</responses_200>
<responses_404>0</responses_404>
<responses_other>4</responses_other>
<result>0</result>
<render>598</render>
<fullyLoaded>20128</fullyLoaded>
<cached>0</cached>
<docTime>18048</docTime>
<domTime>0</domTime>
<score_cache>27</score_cache>
<score_cdn>100</score_cdn>
<score_gzip>100</score_gzip>
<score_cookies>-1</score_cookies>
<score_keep-alive>100</score_keep-alive>
<score_minify>-1</score_minify>
<score_combine>100</score_combine>
<score_compress>-1</score_compress>
<score_etags>-1</score_etags>
<gzip_total>31398</gzip_total>
<gzip_savings>0</gzip_savings>
<minify_total>0</minify_total>
<minify_savings>0</minify_savings>
<image_total>0</image_total>
<image_savings>0</image_savings>
<optimization_checked>1</optimization_checked>
<aft>0</aft>
<domElements>319</domElements>
<pageSpeedVersion>2</pageSpeedVersion>
<titleTime>3678</titleTime>
<loadEventStart>17835</loadEventStart>
<loadEventEnd>17844</loadEventEnd>
<domContentLoadedEventStart>2890</domContentLoadedEventStart>
<domContentLoadedEventEnd>2890</domContentLoadedEventEnd>
<lastVisualChange>19234</lastVisualChange>
<server_count>1</server_count>
<server_rtt>0</server_rtt>
<adult_site>0</adult_site>
<fixed_viewport>1</fixed_viewport>
<score_progressive_jpeg>-1</score_progressive_jpeg>
<firstPaint>7639</firstPaint>
<docCPUms>14773</docCPUms>
<fullyLoadedCPUms>17301</fullyLoadedCPUms>
<docCPUpct>81</docCPUpct>
<fullyLoadedCPUpct>73</fullyLoadedCPUpct>
<isResponsive>-1</isResponsive>
<date>1489358677</date>
<userTime.is>7253</userTime.is>
<userTime.e_is>7369</userTime.e_is>
<userTime.ofv>7423</userTime.ofv>
<userTime.mbv>7553</userTime.mbv>
<userTime.aaa>10954</userTime.aaa>
<userTime.pc>17774</userTime.pc>
<userTime.ol>17826</userTime.ol>
<userTime>17826</userTime>
<SpeedIndex>11352</SpeedIndex>
<visualComplete>11750</visualComplete>
<chromeUserTiming.fetchStart>1</chromeUserTiming.fetchStart>
<chromeUserTiming.unloadEventStart>2678</chromeUserTiming.unloadEventStart>
<chromeUserTiming.unloadEventEnd>2678</chromeUserTiming.unloadEventEnd>
<chromeUserTiming.responseEnd>2674</chromeUserTiming.responseEnd>
<chromeUserTiming.firstMeaningfulPaint>7639</chromeUserTiming.firstMeaningfulPaint>
<chromeUserTiming.loadEventStart>17834</chromeUserTiming.loadEventStart>
<chromeUserTiming.loadEventEnd>17844</chromeUserTiming.loadEventEnd>
<run>2</run>
<effectiveBps>74001</effectiveBps>
<effectiveBpsDoc>80116</effectiveBpsDoc>
<avgRun>1</avgRun>
</firstView>
</average>
<standardDeviation>
<firstView>
<loadTime>2360</loadTime>
<TTFB>801</TTFB>
<bytesOut>1453</bytesOut>
<bytesOutDoc>922</bytesOutDoc>
<bytesIn>5326</bytesIn>
<bytesInDoc>5176</bytesInDoc>
<connections>1</connections>
<requests>0</requests>
<requestsFull>0</requestsFull>
<requestsDoc>0</requestsDoc>
<responses_200>0</responses_200>
<responses_404>0</responses_404>
<responses_other>0</responses_other>
<result>0</result>
<render>39</render>
<fullyLoaded>3450</fullyLoaded>
<cached>0</cached>
<docTime>2360</docTime>
<domTime>0</domTime>
<score_cache>0</score_cache>
<score_cdn>0</score_cdn>
<score_gzip>0</score_gzip>
<score_cookies>0</score_cookies>
<score_keep-alive>0</score_keep-alive>
<score_minify>0</score_minify>
<score_combine>0</score_combine>
<score_compress>0</score_compress>
<score_etags>0</score_etags>
<gzip_total>66</gzip_total>
<gzip_savings>0</gzip_savings>
<minify_total>0</minify_total>
<minify_savings>0</minify_savings>
<image_total>0</image_total>
<image_savings>0</image_savings>
<optimization_checked>0</optimization_checked>
<aft>0</aft>
<domElements>0</domElements>
<pageSpeedVersion>0</pageSpeedVersion>
<titleTime>738</titleTime>
<loadEventStart>2274</loadEventStart>
<loadEventEnd>2277</loadEventEnd>
<domContentLoadedEventStart>939</domContentLoadedEventStart>
<domContentLoadedEventEnd>939</domContentLoadedEventEnd>
<lastVisualChange>2253</lastVisualChange>
<server_count>0</server_count>
<server_rtt>0</server_rtt>
<adult_site>0</adult_site>
<fixed_viewport>0</fixed_viewport>
<score_progressive_jpeg>0</score_progressive_jpeg>
<firstPaint>1329</firstPaint>
<docCPUms>1669</docCPUms>
<fullyLoadedCPUms>2028</fullyLoadedCPUms>
<docCPUpct>1</docCPUpct>
<fullyLoadedCPUpct>2</fullyLoadedCPUpct>
<isResponsive>0</isResponsive>
<date>22</date>
<userTime.is>1364</userTime.is>
<userTime.e_is>1379</userTime.e_is>
<userTime.ofv>1379</userTime.ofv>
<userTime.mbv>1389</userTime.mbv>
<userTime.aaa>1336</userTime.aaa>
<userTime.pc>2251</userTime.pc>
<userTime.ol>2282</userTime.ol>
<userTime>2282</userTime>
<SpeedIndex>1119</SpeedIndex>
<visualComplete>1050</visualComplete>
<chromeUserTiming.fetchStart>0</chromeUserTiming.fetchStart>
<chromeUserTiming.unloadEventStart>882</chromeUserTiming.unloadEventStart>
<chromeUserTiming.unloadEventEnd>882</chromeUserTiming.unloadEventEnd>
<chromeUserTiming.responseEnd>882</chromeUserTiming.responseEnd>
<chromeUserTiming.firstMeaningfulPaint>1330</chromeUserTiming.firstMeaningfulPaint>
<chromeUserTiming.loadEventStart>2274</chromeUserTiming.loadEventStart>
<chromeUserTiming.loadEventEnd>2277</chromeUserTiming.loadEventEnd>
<run>0</run>
<effectiveBps>10113</effectiveBps>
<effectiveBpsDoc>7138</effectiveBpsDoc>
<avgRun/>
</firstView>
</standardDeviation>
<median>
<firstView>
<run>2</run>
<tester>WIN-V9F8885QKK2-165.124.182.230</tester>
<URL>https://www.washingtonpost.com/amphtml/news/the-fix/wp/2017/02/05/how-washington-state-became-the-epicenter-of-resistance-to-trumps-agenda/</URL>
<loadTime>15687</loadTime>
<TTFB>473</TTFB>
<bytesOut>50384</bytesOut>
<bytesOutDoc>40946</bytesOutDoc>
<bytesIn>1363072</bytesIn>
<bytesInDoc>1327496</bytesInDoc>
<connections>20</connections>
<requests>52</requests>
<requestsFull>52</requestsFull>
<requestsDoc>51</requestsDoc>
<responses_200>48</responses_200>
<responses_404>0</responses_404>
<responses_other>4</responses_other>
<result>0</result>
<render>558</render>
<fullyLoaded>16678</fullyLoaded>
<cached>0</cached>
<docTime>15687</docTime>
<domTime>0</domTime>
<score_cache>27</score_cache>
<score_cdn>100</score_cdn>
<score_gzip>100</score_gzip>
<score_cookies>-1</score_cookies>
<score_keep-alive>100</score_keep-alive>
<score_minify>-1</score_minify>
<score_combine>100</score_combine>
<score_compress>-1</score_compress>
<score_etags>-1</score_etags>
<gzip_total>31331</gzip_total>
<gzip_savings>0</gzip_savings>
<minify_total>0</minify_total>
<minify_savings>0</minify_savings>
<image_total>0</image_total>
<image_savings>0</image_savings>
<optimization_checked>1</optimization_checked>
<aft>0</aft>
<domElements>319</domElements>
<pageSpeedVersion>1.9</pageSpeedVersion>
<title>How Washington state became the epicenter of resistance to Trump&amp;rsquo;s agenda</title>
<titleTime>2939</titleTime>
<loadEventStart>15561</loadEventStart>
<loadEventEnd>15566</loadEventEnd>
<domContentLoadedEventStart>1951</domContentLoadedEventStart>
<domContentLoadedEventEnd>1951</domContentLoadedEventEnd>
<lastVisualChange>16980</lastVisualChange>
<browser_name>Google Chrome</browser_name>
<browser_version>56.0.2924.87</browser_version>
<server_count>1</server_count>
<server_rtt>0</server_rtt>
<base_page_cdn>Instart Logic</base_page_cdn>
<adult_site>0</adult_site>
<fixed_viewport>1</fixed_viewport>
<score_progressive_jpeg>-1</score_progressive_jpeg>
<firstPaint>6309</firstPaint>
<docCPUms>13104.084</docCPUms>
<fullyLoadedCPUms>15272.498</fullyLoadedCPUms>
<docCPUpct>82</docCPUpct>
<fullyLoadedCPUpct>75</fullyLoadedCPUpct>
<isResponsive>-1</isResponsive>
<date>1489358699</date>
<userTime.is>5889</userTime.is>
<userTimes>
<is>5889</is>
<e_is>5990</e_is>
<ofv>6044</ofv>
<mbv>6164</mbv>
<aaa>9618</aaa>
<pc>15522</pc>
<ol>15544</ol>
</userTimes>
<userTime.e_is>5990</userTime.e_is>
<userTime.ofv>6044</userTime.ofv>
<userTime.mbv>6164</userTime.mbv>
<userTime.aaa>9618</userTime.aaa>
<userTime.pc>15522</userTime.pc>
<userTime.ol>15544</userTime.ol>
<userTime>15544</userTime>
<SpeedIndex>10233</SpeedIndex>
<visualComplete>10700</visualComplete>
<chromeUserTiming>
<value>
<name>fetchStart</name>
<time>1</time>
</value>
<value>
<name>unloadEventStart</name>
<time>1795</time>
</value>
<value>
<name>unloadEventEnd</name>
<time>1795</time>
</value>
<value>
<name>responseEnd</name>
<time>1791</time>
</value>
<value>
<name>firstMeaningfulPaint</name>
<time>6308</time>
</value>
<value>
<name>loadEventStart</name>
<time>15560</time>
</value>
<value>
<name>loadEventEnd</name>
<time>15566</time>
</value>
</chromeUserTiming>
<chromeUserTiming.fetchStart>1</chromeUserTiming.fetchStart>
<chromeUserTiming.unloadEventStart>1795</chromeUserTiming.unloadEventStart>
<chromeUserTiming.unloadEventEnd>1795</chromeUserTiming.unloadEventEnd>
<chromeUserTiming.responseEnd>1791</chromeUserTiming.responseEnd>
<chromeUserTiming.firstMeaningfulPaint>6308</chromeUserTiming.firstMeaningfulPaint>
<chromeUserTiming.loadEventStart>15560</chromeUserTiming.loadEventStart>
<chromeUserTiming.loadEventEnd>15566</chromeUserTiming.loadEventEnd>
<run>2</run>
<effectiveBps>84114</effectiveBps>
<effectiveBpsDoc>87254</effectiveBpsDoc>
<consoleLog>
<entry>
<source>console-api</source>
<level>info</level>
<message/>
<url>https://cdn.ampproject.org/v0.js</url>
<line>384</line>
</entry>
<entry>
<source>console-api</source>
<level>error</level>
<message>Authorization failed: : timeout???</message>
<url>https://cdn.ampproject.org/v0.js</url>
<line>70</line>
</entry>
<entry>
<source>console-api</source>
<level>log</level>
<message>boomerang.nt: [info] This user agent supports NavigationTiming.</message>
<url>https://js.washingtonpost.com/wp-stat/rum/wprum.min.js</url>
<line>1</line>
</entry>
<entry>
<source>console-api</source>
<level>log</level>
<message>pt.fetchStart: 1489358706996</message>
<url>https://js.washingtonpost.com/wp-stat/rum/wprum.min.js</url>
<line>1</line>
</entry>
<entry>
<source>console-api</source>
<level>log</level>
<message>boomerang: [debug] Checking if we can send beacon</message>
<url>https://js.washingtonpost.com/wp-stat/rum/wprum.min.js</url>
<line>1</line>
</entry>
<entry>
<source>console-api</source>
<level>log</level>
<message>boomerang: [debug] Sending url: //rumds.wpdigital.net/metrics/?rum=%7B%22redt%22%3A0%2C%22nl%22%3A1657%2C%22dns%22%3A0%2C%22tcp%22%3A667%2C%22rest%22%3A505%2C%22domt%22%3A6743%2C%22uplt%22%3A8060%2C%22url%22%3A%22https%3A%2F%2Fjs.washingtonpost.com%2Fnews%2Fthe-fix%2Fwp%2F2017%2F02%2F05%2Fhow-washington-state-became-the-epicenter-of-resistance-to-trumps-agenda%2F%3Fpwa%3Doff%26resType%3Dtracking%26tref%3Damphtml%23amp%3D1%22%2C%22site%22%3A%22js.washingtonpost.com%22%2C%22title%22%3A%22How%20Washington%20state%20became%20the%20epicenter%20of%20resistance%20to%20Trump%E2%80%99s%20agenda%20-%20The%20Washington%20Post%22%2C%22domn%22%3A63%2C%22jhs%22%3A10000000%2C%22fpt%22%3A0%2C%22section%22%3A%22politics%22%2C%22cntt%22%3A%22blog%22%7Dv=0.9u=https%3A%2F%2Fjs.washingtonpost.com%2Fnews%2Fthe-fix%2Fwp%2F2017%2F02%2F05%2Fhow-washington-state-became-the-epicenter-of-resistance-to-trumps-agenda%2F%3Fpwa%3Doff%26resType%3Dtracking%26tref%3Damphtmlif=</message>
<url>https://js.washingtonpost.com/wp-stat/rum/wprum.min.js</url>
<line>1</line>
</entry>
<entry>
<source>console-api</source>
<level>error</level>
<message>Failed to register a ServiceWorker: An SSL certificate error occurred when fetching the script.</message>
<url>https://cdn.ampproject.org/v0.js</url>
<line>70</line>
</entry>
</consoleLog>
</firstView>
</median>
<run>
<id>1</id>
<firstView>
<tester>WIN-V9F8885QKK2-165.124.182.230</tester>
<results>
<URL>https://www.washingtonpost.com/amphtml/news/the-fix/wp/2017/02/05/how-washington-state-became-the-epicenter-of-resistance-to-trumps-agenda/</URL>
<loadTime>20408</loadTime>
<TTFB>2076</TTFB>
<bytesOut>53290</bytesOut>
<bytesOutDoc>42790</bytesOutDoc>
<bytesIn>1373724</bytesIn>
<bytesInDoc>1337848</bytesInDoc>
<connections>22</connections>
<requests>53</requests>
<requestsFull>53</requestsFull>
<requestsDoc>51</requestsDoc>
<responses_200>49</responses_200>
<responses_404>0</responses_404>
<responses_other>4</responses_other>
<result>0</result>
<render>637</render>
<fullyLoaded>23578</fullyLoaded>
<cached>0</cached>
<docTime>20408</docTime>
<domTime>0</domTime>
<score_cache>27</score_cache>
<score_cdn>100</score_cdn>
<score_gzip>100</score_gzip>
<score_cookies>-1</score_cookies>
<score_keep-alive>100</score_keep-alive>
<score_minify>-1</score_minify>
<score_combine>100</score_combine>
<score_compress>-1</score_compress>
<score_etags>-1</score_etags>
<gzip_total>31464</gzip_total>
<gzip_savings>0</gzip_savings>
<minify_total>0</minify_total>
<minify_savings>0</minify_savings>
<image_total>0</image_total>
<image_savings>0</image_savings>
<optimization_checked>1</optimization_checked>
<aft>0</aft>
<domElements>319</domElements>
<pageSpeedVersion>1.9</pageSpeedVersion>
<title>How Washington state became the epicenter of resistance to Trump&amp;rsquo;s agenda</title>
<titleTime>4416</titleTime>
<loadEventStart>20109</loadEventStart>
<loadEventEnd>20121</loadEventEnd>
<domContentLoadedEventStart>3829</domContentLoadedEventStart>
<domContentLoadedEventEnd>3829</domContentLoadedEventEnd>
<lastVisualChange>21487</lastVisualChange>
<browser_name>Google Chrome</browser_name>
<browser_version>56.0.2924.87</browser_version>
<server_count>1</server_count>
<server_rtt>0</server_rtt>
<base_page_cdn>Instart Logic</base_page_cdn>
<adult_site>0</adult_site>
<fixed_viewport>1</fixed_viewport>
<score_progressive_jpeg>-1</score_progressive_jpeg>
<firstPaint>8968</firstPaint>
<docCPUms>16442.505</docCPUms>
<fullyLoadedCPUms>19328.524</fullyLoadedCPUms>
<docCPUpct>79</docCPUpct>
<fullyLoadedCPUpct>71</fullyLoadedCPUpct>
<isResponsive>-1</isResponsive>
<date>1489358655</date>
<userTime.is>8617</userTime.is>
<userTimes>
<is>8617</is>
<e_is>8748</e_is>
<ofv>8802</ofv>
<mbv>8942</mbv>
<aaa>12290</aaa>
<pc>20025</pc>
<ol>20108</ol>
</userTimes>
<userTime.e_is>8748</userTime.e_is>
<userTime.ofv>8802</userTime.ofv>
<userTime.mbv>8942</userTime.mbv>
<userTime.aaa>12290</userTime.aaa>
<userTime.pc>20025</userTime.pc>
<userTime.ol>20108</userTime.ol>
<userTime>20108</userTime>
<SpeedIndex>12471</SpeedIndex>
<visualComplete>12800</visualComplete>
<chromeUserTiming>
<value>
<name>fetchStart</name>
<time>1</time>
</value>
<value>
<name>unloadEventStart</name>
<time>3560</time>
</value>
<value>
<name>unloadEventEnd</name>
<time>3560</time>
</value>
<value>
<name>responseEnd</name>
<time>3556</time>
</value>
<value>
<name>firstMeaningfulPaint</name>
<time>8969</time>
</value>
<value>
<name>loadEventStart</name>
<time>20108</time>
</value>
<value>
<name>loadEventEnd</name>
<time>20121</time>
</value>
</chromeUserTiming>
<chromeUserTiming.fetchStart>1</chromeUserTiming.fetchStart>
<chromeUserTiming.unloadEventStart>3560</chromeUserTiming.unloadEventStart>
<chromeUserTiming.unloadEventEnd>3560</chromeUserTiming.unloadEventEnd>
<chromeUserTiming.responseEnd>3556</chromeUserTiming.responseEnd>
<chromeUserTiming.firstMeaningfulPaint>8969</chromeUserTiming.firstMeaningfulPaint>
<chromeUserTiming.loadEventStart>20108</chromeUserTiming.loadEventStart>
<chromeUserTiming.loadEventEnd>20121</chromeUserTiming.loadEventEnd>
<run>1</run>
<effectiveBps>63888</effectiveBps>
<effectiveBpsDoc>72978</effectiveBpsDoc>
</results>
<pages>
<details>http://104.198.155.24/details.php?test=170312_CK_a6a1d62a7f6a2821f8cb6be7de39699b&amp;run=1</details>
<checklist>http://104.198.155.24/performance_optimization.php?test=170312_CK_a6a1d62a7f6a2821f8cb6be7de39699b&amp;run=1</checklist>
<breakdown>http://104.198.155.24/breakdown.php?test=170312_CK_a6a1d62a7f6a2821f8cb6be7de39699b&amp;run=1</breakdown>
<domains>http://104.198.155.24/domains.php?test=170312_CK_a6a1d62a7f6a2821f8cb6be7de39699b&amp;run=1</domains>
<screenShot>http://104.198.155.24/screen_shot.php?test=170312_CK_a6a1d62a7f6a2821f8cb6be7de39699b&amp;run=1</screenShot>
</pages>
<thumbnails>
<waterfall>http://104.198.155.24/result/170312_CK_a6a1d62a7f6a2821f8cb6be7de39699b/1_waterfall_thumb.png</waterfall>
<checklist>http://104.198.155.24/result/170312_CK_a6a1d62a7f6a2821f8cb6be7de39699b/1_optimization_thumb.png</checklist>
<screenShot>http://104.198.155.24/result/170312_CK_a6a1d62a7f6a2821f8cb6be7de39699b/1_screen_thumb.jpg</screenShot>
</thumbnails>
<images>
<waterfall>http://104.198.155.24/results/17/03/12/CK/a6a1d62a7f6a2821f8cb6be7de39699b/1_waterfall.png</waterfall>
<connectionView>http://104.198.155.24/results/17/03/12/CK/a6a1d62a7f6a2821f8cb6be7de39699b/1_connection.png</connectionView>
<checklist>http://104.198.155.24/results/17/03/12/CK/a6a1d62a7f6a2821f8cb6be7de39699b/1_optimization.png</checklist>
<screenShot>http://104.198.155.24/getfile.php?test=170312_CK_a6a1d62a7f6a2821f8cb6be7de39699b&amp;file=1_screen.jpg</screenShot>
</images>
<rawData><headers>http://104.198.155.24/results/17/03/12/CK/a6a1d62a7f6a2821f8cb6be7de39699b/1_report.txt</headers>
<pageData>http://104.198.155.24/results/17/03/12/CK/a6a1d62a7f6a2821f8cb6be7de39699b/1_IEWPG.txt</pageData>
<requestsData>http://104.198.155.24/results/17/03/12/CK/a6a1d62a7f6a2821f8cb6be7de39699b/1_IEWTR.txt</requestsData>
<utilization>http://104.198.155.24/results/17/03/12/CK/a6a1d62a7f6a2821f8cb6be7de39699b/1_progress.csv</utilization>
</rawData>
<videoFrames>
<frame>
<time>0</time>
<image>http://104.198.155.24/getfile.php?test=170312_CK_a6a1d62a7f6a2821f8cb6be7de39699b&amp;video=video_1&amp;file=frame_0000.jpg</image>
<VisuallyComplete>0</VisuallyComplete>
</frame>
<frame>
<time>600</time>
<image>http://104.198.155.24/getfile.php?test=170312_CK_a6a1d62a7f6a2821f8cb6be7de39699b&amp;video=video_1&amp;file=frame_0006.jpg</image>
<VisuallyComplete>0</VisuallyComplete>
</frame>
<frame>
<time>5400</time>
<image>http://104.198.155.24/getfile.php?test=170312_CK_a6a1d62a7f6a2821f8cb6be7de39699b&amp;video=video_1&amp;file=frame_0054.jpg</image>
<VisuallyComplete>0</VisuallyComplete>
</frame>
<frame>
<time>5500</time>
<image>http://104.198.155.24/getfile.php?test=170312_CK_a6a1d62a7f6a2821f8cb6be7de39699b&amp;video=video_1&amp;file=frame_0055.jpg</image>
<VisuallyComplete>1</VisuallyComplete>
</frame>
<frame>
<time>5700</time>
<image>http://104.198.155.24/getfile.php?test=170312_CK_a6a1d62a7f6a2821f8cb6be7de39699b&amp;video=video_1&amp;file=frame_0057.jpg</image>
<VisuallyComplete>0</VisuallyComplete>
</frame>
<frame>
<time>9500</time>
<image>http://104.198.155.24/getfile.php?test=170312_CK_a6a1d62a7f6a2821f8cb6be7de39699b&amp;video=video_1&amp;file=frame_0095.jpg</image>
<VisuallyComplete>0</VisuallyComplete>
</frame>
<frame>
<time>9800</time>
<image>http://104.198.155.24/getfile.php?test=170312_CK_a6a1d62a7f6a2821f8cb6be7de39699b&amp;video=video_1&amp;file=frame_0098.jpg</image>
<VisuallyComplete>14</VisuallyComplete>
</frame>
<frame>
<time>10100</time>
<image>http://104.198.155.24/getfile.php?test=170312_CK_a6a1d62a7f6a2821f8cb6be7de39699b&amp;video=video_1&amp;file=frame_0101.jpg</image>
<VisuallyComplete>13</VisuallyComplete>
</frame>
<frame>
<time>10400</time>
<image>http://104.198.155.24/getfile.php?test=170312_CK_a6a1d62a7f6a2821f8cb6be7de39699b&amp;video=video_1&amp;file=frame_0104.jpg</image>
<VisuallyComplete>13</VisuallyComplete>
</frame>
<frame>
<time>10700</time>
<image>http://104.198.155.24/getfile.php?test=170312_CK_a6a1d62a7f6a2821f8cb6be7de39699b&amp;video=video_1&amp;file=frame_0107.jpg</image>
<VisuallyComplete>13</VisuallyComplete>
</frame>
<frame>
<time>10900</time>
<image>http://104.198.155.24/getfile.php?test=170312_CK_a6a1d62a7f6a2821f8cb6be7de39699b&amp;video=video_1&amp;file=frame_0109.jpg</image>
<VisuallyComplete>14</VisuallyComplete>
</frame>
<frame>
<time>11100</time>
<image>http://104.198.155.24/getfile.php?test=170312_CK_a6a1d62a7f6a2821f8cb6be7de39699b&amp;video=video_1&amp;file=frame_0111.jpg</image>
<VisuallyComplete>13</VisuallyComplete>
</frame>
<frame>
<time>11800</time>
<image>http://104.198.155.24/getfile.php?test=170312_CK_a6a1d62a7f6a2821f8cb6be7de39699b&amp;video=video_1&amp;file=frame_0118.jpg</image>
<VisuallyComplete>14</VisuallyComplete>
</frame>
<frame>
<time>11900</time>
<image>http://104.198.155.24/getfile.php?test=170312_CK_a6a1d62a7f6a2821f8cb6be7de39699b&amp;video=video_1&amp;file=frame_0119.jpg</image>
<VisuallyComplete>13</VisuallyComplete>
</frame>
<frame>
<time>12800</time>
<image>http://104.198.155.24/getfile.php?test=170312_CK_a6a1d62a7f6a2821f8cb6be7de39699b&amp;video=video_1&amp;file=frame_0128.jpg</image>
<VisuallyComplete>100</VisuallyComplete>
</frame>
<frame>
<time>18400</time>
<image>http://104.198.155.24/getfile.php?test=170312_CK_a6a1d62a7f6a2821f8cb6be7de39699b&amp;video=video_1&amp;file=frame_0184.jpg</image>
<VisuallyComplete>98</VisuallyComplete>
</frame>
<frame>
<time>20000</time>
<image>http://104.198.155.24/getfile.php?test=170312_CK_a6a1d62a7f6a2821f8cb6be7de39699b&amp;video=video_1&amp;file=frame_0200.jpg</image>
<VisuallyComplete>97</VisuallyComplete>
</frame>
<frame>
<time>20700</time>
<image>http://104.198.155.24/getfile.php?test=170312_CK_a6a1d62a7f6a2821f8cb6be7de39699b&amp;video=video_1&amp;file=frame_0207.jpg</image>
<VisuallyComplete>98</VisuallyComplete>
</frame>
<frame>
<time>20900</time>
<image>http://104.198.155.24/getfile.php?test=170312_CK_a6a1d62a7f6a2821f8cb6be7de39699b&amp;video=video_1&amp;file=frame_0209.jpg</image>
<VisuallyComplete>98</VisuallyComplete>
</frame>
<frame>
<time>21500</time>
<image>http://104.198.155.24/getfile.php?test=170312_CK_a6a1d62a7f6a2821f8cb6be7de39699b&amp;video=video_1&amp;file=frame_0215.jpg</image>
<VisuallyComplete>100</VisuallyComplete>
</frame>
</videoFrames>
<consoleLog>
<entry>
<source>console-api</source>
<level>info</level>
<message/>
<url>https://cdn.ampproject.org/v0.js</url>
<line>384</line>
</entry>
<entry>
<source>console-api</source>
<level>error</level>
<message>Authorization failed: : timeout???</message>
<url>https://cdn.ampproject.org/v0.js</url>
<line>70</line>
</entry>
<entry>
<source>console-api</source>
<level>log</level>
<message>boomerang.nt: [info] This user agent supports NavigationTiming.</message>
<url>https://js.washingtonpost.com/wp-stat/rum/wprum.min.js</url>
<line>1</line>
</entry>
<entry>
<source>console-api</source>
<level>log</level>
<message>pt.fetchStart: 1489358665891</message>
<url>https://js.washingtonpost.com/wp-stat/rum/wprum.min.js</url>
<line>1</line>
</entry>
<entry>
<source>console-api</source>
<level>log</level>
<message>boomerang: [debug] Checking if we can send beacon</message>
<url>https://js.washingtonpost.com/wp-stat/rum/wprum.min.js</url>
<line>1</line>
</entry>
<entry>
<source>console-api</source>
<level>log</level>
<message>boomerang: [debug] Sending url: //rumds.wpdigital.net/metrics/?rum=%7B%22redt%22%3A0%2C%22nl%22%3A2070%2C%22dns%22%3A0%2C%22tcp%22%3A696%2C%22rest%22%3A640%2C%22domt%22%3A9004%2C%22uplt%22%3A10137%2C%22url%22%3A%22https%3A%2F%2Fjs.washingtonpost.com%2Fnews%2Fthe-fix%2Fwp%2F2017%2F02%2F05%2Fhow-washington-state-became-the-epicenter-of-resistance-to-trumps-agenda%2F%3Fpwa%3Doff%26resType%3Dtracking%26tref%3Damphtml%23amp%3D1%22%2C%22site%22%3A%22js.washingtonpost.com%22%2C%22title%22%3A%22How%20Washington%20state%20became%20the%20epicenter%20of%20resistance%20to%20Trump%E2%80%99s%20agenda%20-%20The%20Washington%20Post%22%2C%22domn%22%3A63%2C%22jhs%22%3A10000000%2C%22fpt%22%3A0%2C%22section%22%3A%22politics%22%2C%22cntt%22%3A%22blog%22%7Dv=0.9u=https%3A%2F%2Fjs.washingtonpost.com%2Fnews%2Fthe-fix%2Fwp%2F2017%2F02%2F05%2Fhow-washington-state-became-the-epicenter-of-resistance-to-trumps-agenda%2F%3Fpwa%3Doff%26resType%3Dtracking%26tref%3Damphtmlif=</message>
<url>https://js.washingtonpost.com/wp-stat/rum/wprum.min.js</url>
<line>1</line>
</entry>
<entry>
<source>console-api</source>
<level>error</level>
<message>Failed to register a ServiceWorker: An SSL certificate error occurred when fetching the script.</message>
<url>https://cdn.ampproject.org/v0.js</url>
<line>70</line>
</entry>
</consoleLog>
</firstView>
</run>
<run>
<id>2</id>
<firstView>
<tester>WIN-V9F8885QKK2-165.124.182.230</tester>
<results>
<URL>https://www.washingtonpost.com/amphtml/news/the-fix/wp/2017/02/05/how-washington-state-became-the-epicenter-of-resistance-to-trumps-agenda/</URL>
<loadTime>15687</loadTime>
<TTFB>473</TTFB>
<bytesOut>50384</bytesOut>
<bytesOutDoc>40946</bytesOutDoc>
<bytesIn>1363072</bytesIn>
<bytesInDoc>1327496</bytesInDoc>
<connections>20</connections>
<requests>52</requests>
<requestsFull>52</requestsFull>
<requestsDoc>51</requestsDoc>
<responses_200>48</responses_200>
<responses_404>0</responses_404>
<responses_other>4</responses_other>
<result>0</result>
<render>558</render>
<fullyLoaded>16678</fullyLoaded>
<cached>0</cached>
<docTime>15687</docTime>
<domTime>0</domTime>
<score_cache>27</score_cache>
<score_cdn>100</score_cdn>
<score_gzip>100</score_gzip>
<score_cookies>-1</score_cookies>
<score_keep-alive>100</score_keep-alive>
<score_minify>-1</score_minify>
<score_combine>100</score_combine>
<score_compress>-1</score_compress>
<score_etags>-1</score_etags>
<gzip_total>31331</gzip_total>
<gzip_savings>0</gzip_savings>
<minify_total>0</minify_total>
<minify_savings>0</minify_savings>
<image_total>0</image_total>
<image_savings>0</image_savings>
<optimization_checked>1</optimization_checked>
<aft>0</aft>
<domElements>319</domElements>
<pageSpeedVersion>1.9</pageSpeedVersion>
<title>How Washington state became the epicenter of resistance to Trump&amp;rsquo;s agenda</title>
<titleTime>2939</titleTime>
<loadEventStart>15561</loadEventStart>
<loadEventEnd>15566</loadEventEnd>
<domContentLoadedEventStart>1951</domContentLoadedEventStart>
<domContentLoadedEventEnd>1951</domContentLoadedEventEnd>
<lastVisualChange>16980</lastVisualChange>
<browser_name>Google Chrome</browser_name>
<browser_version>56.0.2924.87</browser_version>
<server_count>1</server_count>
<server_rtt>0</server_rtt>
<base_page_cdn>Instart Logic</base_page_cdn>
<adult_site>0</adult_site>
<fixed_viewport>1</fixed_viewport>
<score_progressive_jpeg>-1</score_progressive_jpeg>
<firstPaint>6309</firstPaint>
<docCPUms>13104.084</docCPUms>
<fullyLoadedCPUms>15272.498</fullyLoadedCPUms>
<docCPUpct>82</docCPUpct>
<fullyLoadedCPUpct>75</fullyLoadedCPUpct>
<isResponsive>-1</isResponsive>
<date>1489358699</date>
<userTime.is>5889</userTime.is>
<userTimes>
<is>5889</is>
<e_is>5990</e_is>
<ofv>6044</ofv>
<mbv>6164</mbv>
<aaa>9618</aaa>
<pc>15522</pc>
<ol>15544</ol>
</userTimes>
<userTime.e_is>5990</userTime.e_is>
<userTime.ofv>6044</userTime.ofv>
<userTime.mbv>6164</userTime.mbv>
<userTime.aaa>9618</userTime.aaa>
<userTime.pc>15522</userTime.pc>
<userTime.ol>15544</userTime.ol>
<userTime>15544</userTime>
<SpeedIndex>10233</SpeedIndex>
<visualComplete>10700</visualComplete>
<chromeUserTiming>
<value>
<name>fetchStart</name>
<time>1</time>
</value>
<value>
<name>unloadEventStart</name>
<time>1795</time>
</value>
<value>
<name>unloadEventEnd</name>
<time>1795</time>
</value>
<value>
<name>responseEnd</name>
<time>1791</time>
</value>
<value>
<name>firstMeaningfulPaint</name>
<time>6308</time>
</value>
<value>
<name>loadEventStart</name>
<time>15560</time>
</value>
<value>
<name>loadEventEnd</name>
<time>15566</time>
</value>
</chromeUserTiming>
<chromeUserTiming.fetchStart>1</chromeUserTiming.fetchStart>
<chromeUserTiming.unloadEventStart>1795</chromeUserTiming.unloadEventStart>
<chromeUserTiming.unloadEventEnd>1795</chromeUserTiming.unloadEventEnd>
<chromeUserTiming.responseEnd>1791</chromeUserTiming.responseEnd>
<chromeUserTiming.firstMeaningfulPaint>6308</chromeUserTiming.firstMeaningfulPaint>
<chromeUserTiming.loadEventStart>15560</chromeUserTiming.loadEventStart>
<chromeUserTiming.loadEventEnd>15566</chromeUserTiming.loadEventEnd>
<run>2</run>
<effectiveBps>84114</effectiveBps>
<effectiveBpsDoc>87254</effectiveBpsDoc>
</results>
<pages>
<details>http://104.198.155.24/details.php?test=170312_CK_a6a1d62a7f6a2821f8cb6be7de39699b&amp;run=2</details>
<checklist>http://104.198.155.24/performance_optimization.php?test=170312_CK_a6a1d62a7f6a2821f8cb6be7de39699b&amp;run=2</checklist>
<breakdown>http://104.198.155.24/breakdown.php?test=170312_CK_a6a1d62a7f6a2821f8cb6be7de39699b&amp;run=2</breakdown>
<domains>http://104.198.155.24/domains.php?test=170312_CK_a6a1d62a7f6a2821f8cb6be7de39699b&amp;run=2</domains>
<screenShot>http://104.198.155.24/screen_shot.php?test=170312_CK_a6a1d62a7f6a2821f8cb6be7de39699b&amp;run=2</screenShot>
</pages>
<thumbnails>
<waterfall>http://104.198.155.24/result/170312_CK_a6a1d62a7f6a2821f8cb6be7de39699b/2_waterfall_thumb.png</waterfall>
<checklist>http://104.198.155.24/result/170312_CK_a6a1d62a7f6a2821f8cb6be7de39699b/2_optimization_thumb.png</checklist>
<screenShot>http://104.198.155.24/result/170312_CK_a6a1d62a7f6a2821f8cb6be7de39699b/2_screen_thumb.jpg</screenShot>
</thumbnails>
<images>
<waterfall>http://104.198.155.24/results/17/03/12/CK/a6a1d62a7f6a2821f8cb6be7de39699b/2_waterfall.png</waterfall>
<connectionView>http://104.198.155.24/results/17/03/12/CK/a6a1d62a7f6a2821f8cb6be7de39699b/2_connection.png</connectionView>
<checklist>http://104.198.155.24/results/17/03/12/CK/a6a1d62a7f6a2821f8cb6be7de39699b/2_optimization.png</checklist>
<screenShot>http://104.198.155.24/getfile.php?test=170312_CK_a6a1d62a7f6a2821f8cb6be7de39699b&amp;file=2_screen.jpg</screenShot>
</images>
<rawData><headers>http://104.198.155.24/results/17/03/12/CK/a6a1d62a7f6a2821f8cb6be7de39699b/2_report.txt</headers>
<pageData>http://104.198.155.24/results/17/03/12/CK/a6a1d62a7f6a2821f8cb6be7de39699b/2_IEWPG.txt</pageData>
<requestsData>http://104.198.155.24/results/17/03/12/CK/a6a1d62a7f6a2821f8cb6be7de39699b/2_IEWTR.txt</requestsData>
<utilization>http://104.198.155.24/results/17/03/12/CK/a6a1d62a7f6a2821f8cb6be7de39699b/2_progress.csv</utilization>
</rawData>
<videoFrames>
<frame>
<time>0</time>
<image>http://104.198.155.24/getfile.php?test=170312_CK_a6a1d62a7f6a2821f8cb6be7de39699b&amp;video=video_2&amp;file=frame_0000.jpg</image>
<VisuallyComplete>0</VisuallyComplete>
</frame>
<frame>
<time>600</time>
<image>http://104.198.155.24/getfile.php?test=170312_CK_a6a1d62a7f6a2821f8cb6be7de39699b&amp;video=video_2&amp;file=frame_0006.jpg</image>
<VisuallyComplete>0</VisuallyComplete>
</frame>
<frame>
<time>3600</time>
<image>http://104.198.155.24/getfile.php?test=170312_CK_a6a1d62a7f6a2821f8cb6be7de39699b&amp;video=video_2&amp;file=frame_0036.jpg</image>
<VisuallyComplete>0</VisuallyComplete>
</frame>
<frame>
<time>3800</time>
<image>http://104.198.155.24/getfile.php?test=170312_CK_a6a1d62a7f6a2821f8cb6be7de39699b&amp;video=video_2&amp;file=frame_0038.jpg</image>
<VisuallyComplete>0</VisuallyComplete>
</frame>
<frame>
<time>6500</time>
<image>http://104.198.155.24/getfile.php?test=170312_CK_a6a1d62a7f6a2821f8cb6be7de39699b&amp;video=video_2&amp;file=frame_0065.jpg</image>
<VisuallyComplete>0</VisuallyComplete>
</frame>
<frame>
<time>7500</time>
<image>http://104.198.155.24/getfile.php?test=170312_CK_a6a1d62a7f6a2821f8cb6be7de39699b&amp;video=video_2&amp;file=frame_0075.jpg</image>
<VisuallyComplete>14</VisuallyComplete>
</frame>
<frame>
<time>8800</time>
<image>http://104.198.155.24/getfile.php?test=170312_CK_a6a1d62a7f6a2821f8cb6be7de39699b&amp;video=video_2&amp;file=frame_0088.jpg</image>
<VisuallyComplete>13</VisuallyComplete>
</frame>
<frame>
<time>9000</time>
<image>http://104.198.155.24/getfile.php?test=170312_CK_a6a1d62a7f6a2821f8cb6be7de39699b&amp;video=video_2&amp;file=frame_0090.jpg</image>
<VisuallyComplete>13</VisuallyComplete>
</frame>
<frame>
<time>9300</time>
<image>http://104.198.155.24/getfile.php?test=170312_CK_a6a1d62a7f6a2821f8cb6be7de39699b&amp;video=video_2&amp;file=frame_0093.jpg</image>
<VisuallyComplete>13</VisuallyComplete>
</frame>
<frame>
<time>10600</time>
<image>http://104.198.155.24/getfile.php?test=170312_CK_a6a1d62a7f6a2821f8cb6be7de39699b&amp;video=video_2&amp;file=frame_0106.jpg</image>
<VisuallyComplete>99</VisuallyComplete>
</frame>
<frame>
<time>10700</time>
<image>http://104.198.155.24/getfile.php?test=170312_CK_a6a1d62a7f6a2821f8cb6be7de39699b&amp;video=video_2&amp;file=frame_0107.jpg</image>
<VisuallyComplete>100</VisuallyComplete>
</frame>
<frame>
<time>14400</time>
<image>http://104.198.155.24/getfile.php?test=170312_CK_a6a1d62a7f6a2821f8cb6be7de39699b&amp;video=video_2&amp;file=frame_0144.jpg</image>
<VisuallyComplete>100</VisuallyComplete>
</frame>
<frame>
<time>14500</time>
<image>http://104.198.155.24/getfile.php?test=170312_CK_a6a1d62a7f6a2821f8cb6be7de39699b&amp;video=video_2&amp;file=frame_0145.jpg</image>
<VisuallyComplete>98</VisuallyComplete>
</frame>
<frame>
<time>15000</time>
<image>http://104.198.155.24/getfile.php?test=170312_CK_a6a1d62a7f6a2821f8cb6be7de39699b&amp;video=video_2&amp;file=frame_0150.jpg</image>
<VisuallyComplete>99</VisuallyComplete>
</frame>
<frame>
<time>15200</time>
<image>http://104.198.155.24/getfile.php?test=170312_CK_a6a1d62a7f6a2821f8cb6be7de39699b&amp;video=video_2&amp;file=frame_0152.jpg</image>
<VisuallyComplete>98</VisuallyComplete>
</frame>
<frame>
<time>16100</time>
<image>http://104.198.155.24/getfile.php?test=170312_CK_a6a1d62a7f6a2821f8cb6be7de39699b&amp;video=video_2&amp;file=frame_0161.jpg</image>
<VisuallyComplete>98</VisuallyComplete>
</frame>
<frame>
<time>16200</time>
<image>http://104.198.155.24/getfile.php?test=170312_CK_a6a1d62a7f6a2821f8cb6be7de39699b&amp;video=video_2&amp;file=frame_0162.jpg</image>
<VisuallyComplete>98</VisuallyComplete>
</frame>
<frame>
<time>17000</time>
<image>http://104.198.155.24/getfile.php?test=170312_CK_a6a1d62a7f6a2821f8cb6be7de39699b&amp;video=video_2&amp;file=frame_0170.jpg</image>
<VisuallyComplete>100</VisuallyComplete>
</frame>
</videoFrames>
<consoleLog>
<entry>
<source>console-api</source>
<level>info</level>
<message/>
<url>https://cdn.ampproject.org/v0.js</url>
<line>384</line>
</entry>
<entry>
<source>console-api</source>
<level>error</level>
<message>Authorization failed: : timeout???</message>
<url>https://cdn.ampproject.org/v0.js</url>
<line>70</line>
</entry>
<entry>
<source>console-api</source>
<level>log</level>
<message>boomerang.nt: [info] This user agent supports NavigationTiming.</message>
<url>https://js.washingtonpost.com/wp-stat/rum/wprum.min.js</url>
<line>1</line>
</entry>
<entry>
<source>console-api</source>
<level>log</level>
<message>pt.fetchStart: 1489358706996</message>
<url>https://js.washingtonpost.com/wp-stat/rum/wprum.min.js</url>
<line>1</line>
</entry>
<entry>
<source>console-api</source>
<level>log</level>
<message>boomerang: [debug] Checking if we can send beacon</message>
<url>https://js.washingtonpost.com/wp-stat/rum/wprum.min.js</url>
<line>1</line>
</entry>
<entry>
<source>console-api</source>
<level>log</level>
<message>boomerang: [debug] Sending url: //rumds.wpdigital.net/metrics/?rum=%7B%22redt%22%3A0%2C%22nl%22%3A1657%2C%22dns%22%3A0%2C%22tcp%22%3A667%2C%22rest%22%3A505%2C%22domt%22%3A6743%2C%22uplt%22%3A8060%2C%22url%22%3A%22https%3A%2F%2Fjs.washingtonpost.com%2Fnews%2Fthe-fix%2Fwp%2F2017%2F02%2F05%2Fhow-washington-state-became-the-epicenter-of-resistance-to-trumps-agenda%2F%3Fpwa%3Doff%26resType%3Dtracking%26tref%3Damphtml%23amp%3D1%22%2C%22site%22%3A%22js.washingtonpost.com%22%2C%22title%22%3A%22How%20Washington%20state%20became%20the%20epicenter%20of%20resistance%20to%20Trump%E2%80%99s%20agenda%20-%20The%20Washington%20Post%22%2C%22domn%22%3A63%2C%22jhs%22%3A10000000%2C%22fpt%22%3A0%2C%22section%22%3A%22politics%22%2C%22cntt%22%3A%22blog%22%7Dv=0.9u=https%3A%2F%2Fjs.washingtonpost.com%2Fnews%2Fthe-fix%2Fwp%2F2017%2F02%2F05%2Fhow-washington-state-became-the-epicenter-of-resistance-to-trumps-agenda%2F%3Fpwa%3Doff%26resType%3Dtracking%26tref%3Damphtmlif=</message>
<url>https://js.washingtonpost.com/wp-stat/rum/wprum.min.js</url>
<line>1</line>
</entry>
<entry>
<source>console-api</source>
<level>error</level>
<message>Failed to register a ServiceWorker: An SSL certificate error occurred when fetching the script.</message>
<url>https://cdn.ampproject.org/v0.js</url>
<line>70</line>
</entry>
</consoleLog>
</firstView>
</run>
</data>
</response>