<?xml version="1.0" encoding="utf-8"?><response>
<statusCode>200</statusCode>
<statusText>Ok</statusText>
<data>
<testId>170312_FT_febf26e2b0f2dfc23c02ce6f9f77f935</testId>
<summary>http://104.198.155.24/results.php?test=170312_FT_febf26e2b0f2dfc23c02ce6f9f77f935</summary>
<testUrl>https://www.washingtonpost.com/news/worldviews/wp/2017/02/06/breaking-bad-fan-who-dissolved-cops-body-in-acid-is-found-dead-in-prison/</testUrl>
<location>Alex3:Chrome</location>
<from>Alex - &lt;b&gt;Chrome&lt;/b&gt; - &lt;b&gt;custom&lt;/b&gt;</from>
<connectivity>custom</connectivity>
<bwDown>1500</bwDown>
<bwUp>384</bwUp>
<latency>50</latency>
<plr>0</plr>
<mobile>0</mobile>
<completed>Sun, 12 Mar 2017 22:30:14 +0000</completed>
<tester>WIN-V9F8885QKK2-165.124.182.230</tester>
<testerDNS>172.16.192.2</testerDNS>
<runs>2</runs>
<successfulFVRuns>2</successfulFVRuns>
<average>
<firstView>
<loadTime>69092</loadTime>
<TTFB>869</TTFB>
<bytesOut>246392</bytesOut>
<bytesOutDoc>240685</bytesOutDoc>
<bytesIn>3523687</bytesIn>
<bytesInDoc>3516220</bytesInDoc>
<connections>125</connections>
<requests>291</requests>
<requestsFull>291</requestsFull>
<requestsDoc>289</requestsDoc>
<responses_200>205</responses_200>
<responses_404>0</responses_404>
<responses_other>51</responses_other>
<result>0</result>
<render>1106</render>
<fullyLoaded>70559</fullyLoaded>
<cached>0</cached>
<docTime>69092</docTime>
<domTime>0</domTime>
<score_cache>41</score_cache>
<score_cdn>76</score_cdn>
<score_gzip>100</score_gzip>
<score_cookies>-1</score_cookies>
<score_keep-alive>98</score_keep-alive>
<score_minify>-1</score_minify>
<score_combine>100</score_combine>
<score_compress>-1</score_compress>
<score_etags>-1</score_etags>
<gzip_total>54062</gzip_total>
<gzip_savings>0</gzip_savings>
<minify_total>0</minify_total>
<minify_savings>0</minify_savings>
<image_total>0</image_total>
<image_savings>0</image_savings>
<optimization_checked>1</optimization_checked>
<aft>0</aft>
<domElements>1287</domElements>
<pageSpeedVersion>2</pageSpeedVersion>
<titleTime>2027</titleTime>
<loadEventStart>69715</loadEventStart>
<loadEventEnd>69744</loadEventEnd>
<domContentLoadedEventStart>18907</domContentLoadedEventStart>
<domContentLoadedEventEnd>19134</domContentLoadedEventEnd>
<lastVisualChange>64510</lastVisualChange>
<server_count>1</server_count>
<server_rtt>0</server_rtt>
<adult_site>0</adult_site>
<fixed_viewport>1</fixed_viewport>
<score_progressive_jpeg>-1</score_progressive_jpeg>
<firstPaint>9402</firstPaint>
<docCPUms>52237</docCPUms>
<fullyLoadedCPUms>54015</fullyLoadedCPUms>
<docCPUpct>77</docCPUpct>
<fullyLoadedCPUpct>75</fullyLoadedCPUpct>
<isResponsive>-1</isResponsive>
<date>1489357692</date>
<userTime.markFormatInit>34226</userTime.markFormatInit>
<userTime.markUserSyncRequest>34548</userTime.markUserSyncRequest>
<userTime.markPageStart>34650</userTime.markPageStart>
<userTime.markAdRequest>34650</userTime.markAdRequest>
<userTime.markPageEnd>35788</userTime.markPageEnd>
<userTime.markUserSyncResponse>38528</userTime.markUserSyncResponse>
<userTime>38528</userTime>
<SpeedIndex>14140</SpeedIndex>
<visualComplete>21250</visualComplete>
<chromeUserTiming.fetchStart>1</chromeUserTiming.fetchStart>
<chromeUserTiming.unloadEventStart>2054</chromeUserTiming.unloadEventStart>
<chromeUserTiming.unloadEventEnd>2054</chromeUserTiming.unloadEventEnd>
<chromeUserTiming.responseEnd>2124</chromeUserTiming.responseEnd>
<chromeUserTiming.loadEventStart>69714</chromeUserTiming.loadEventStart>
<chromeUserTiming.loadEventEnd>69743</chromeUserTiming.loadEventEnd>
<chromeUserTiming.firstMeaningfulPaint>10408</chromeUserTiming.firstMeaningfulPaint>
<run>2</run>
<effectiveBps>54435</effectiveBps>
<effectiveBpsDoc>56372</effectiveBpsDoc>
<avgRun>1</avgRun>
</firstView>
</average>
<standardDeviation>
<firstView>
<loadTime>16687</loadTime>
<TTFB>243</TTFB>
<bytesOut>23731</bytesOut>
<bytesOutDoc>23700</bytesOutDoc>
<bytesIn>440460</bytesIn>
<bytesInDoc>440690</bytesInDoc>
<connections>8</connections>
<requests>17</requests>
<requestsFull>17</requestsFull>
<requestsDoc>16</requestsDoc>
<responses_200>15</responses_200>
<responses_404>0</responses_404>
<responses_other>1</responses_other>
<result>0</result>
<render>494</render>
<fullyLoaded>15220</fullyLoaded>
<cached>0</cached>
<docTime>16687</docTime>
<domTime>0</domTime>
<score_cache>4</score_cache>
<score_cdn>9</score_cdn>
<score_gzip>0</score_gzip>
<score_cookies>0</score_cookies>
<score_keep-alive>0</score_keep-alive>
<score_minify>0</score_minify>
<score_combine>0</score_combine>
<score_compress>0</score_compress>
<score_etags>0</score_etags>
<gzip_total>2582</gzip_total>
<gzip_savings>0</gzip_savings>
<minify_total>0</minify_total>
<minify_savings>0</minify_savings>
<image_total>0</image_total>
<image_savings>0</image_savings>
<optimization_checked>0</optimization_checked>
<aft>0</aft>
<domElements>1</domElements>
<pageSpeedVersion>0</pageSpeedVersion>
<titleTime>1318</titleTime>
<loadEventStart>15922</loadEventStart>
<loadEventEnd>15929</loadEventEnd>
<domContentLoadedEventStart>2348</domContentLoadedEventStart>
<domContentLoadedEventEnd>2492</domContentLoadedEventEnd>
<lastVisualChange>21720</lastVisualChange>
<server_count>0</server_count>
<server_rtt>0</server_rtt>
<adult_site>0</adult_site>
<fixed_viewport>0</fixed_viewport>
<score_progressive_jpeg>0</score_progressive_jpeg>
<firstPaint>221</firstPaint>
<docCPUms>5826</docCPUms>
<fullyLoadedCPUms>5436</fullyLoadedCPUms>
<docCPUpct>9</docCPUpct>
<fullyLoadedCPUpct>8</fullyLoadedCPUpct>
<isResponsive>0</isResponsive>
<date>54</date>
<userTime.markFormatInit>4237</userTime.markFormatInit>
<userTime.markUserSyncRequest>4443</userTime.markUserSyncRequest>
<userTime.markPageStart>4418</userTime.markPageStart>
<userTime.markAdRequest>4418</userTime.markAdRequest>
<userTime.markPageEnd>4580</userTime.markPageEnd>
<userTime.markUserSyncResponse>4770</userTime.markUserSyncResponse>
<userTime>4770</userTime>
<SpeedIndex>263</SpeedIndex>
<visualComplete>50</visualComplete>
<chromeUserTiming.fetchStart>0</chromeUserTiming.fetchStart>
<chromeUserTiming.unloadEventStart>487</chromeUserTiming.unloadEventStart>
<chromeUserTiming.unloadEventEnd>487</chromeUserTiming.unloadEventEnd>
<chromeUserTiming.responseEnd>481</chromeUserTiming.responseEnd>
<chromeUserTiming.loadEventStart>15923</chromeUserTiming.loadEventStart>
<chromeUserTiming.loadEventEnd>15929</chromeUserTiming.loadEventEnd>
<chromeUserTiming.firstMeaningfulPaint>354</chromeUserTiming.firstMeaningfulPaint>
<run>0</run>
<effectiveBps>18019</effectiveBps>
<effectiveBpsDoc>20047</effectiveBpsDoc>
<avgRun/>
</firstView>
</standardDeviation>
<median>
<firstView>
<run>2</run>
<tester>WIN-V9F8885QKK2-165.124.182.230</tester>
<URL>https://www.washingtonpost.com/news/worldviews/wp/2017/02/06/breaking-bad-fan-who-dissolved-cops-body-in-acid-is-found-dead-in-prison/</URL>
<loadTime>52405</loadTime>
<TTFB>626</TTFB>
<bytesOut>270123</bytesOut>
<bytesOutDoc>264385</bytesOutDoc>
<bytesIn>3964147</bytesIn>
<bytesInDoc>3956910</bytesInDoc>
<connections>133</connections>
<requests>308</requests>
<requestsFull>308</requestsFull>
<requestsDoc>305</requestsDoc>
<responses_200>220</responses_200>
<responses_404>0</responses_404>
<responses_other>52</responses_other>
<result>0</result>
<render>1600</render>
<fullyLoaded>55338</fullyLoaded>
<cached>0</cached>
<docTime>52405</docTime>
<domTime>0</domTime>
<score_cache>37</score_cache>
<score_cdn>67</score_cdn>
<score_gzip>100</score_gzip>
<score_cookies>-1</score_cookies>
<score_keep-alive>98</score_keep-alive>
<score_minify>-1</score_minify>
<score_combine>100</score_combine>
<score_compress>-1</score_compress>
<score_etags>-1</score_etags>
<gzip_total>56644</gzip_total>
<gzip_savings>0</gzip_savings>
<minify_total>0</minify_total>
<minify_savings>0</minify_savings>
<image_total>0</image_total>
<image_savings>0</image_savings>
<optimization_checked>1</optimization_checked>
<aft>0</aft>
<domElements>1285</domElements>
<pageSpeedVersion>1.9</pageSpeedVersion>
<title>&amp;lsquo;Breaking Bad&amp;rsquo; fan who dissolved cop&amp;rsquo;s body in acid is found dead in prison - The Washington Post</title>
<titleTime>709</titleTime>
<loadEventStart>53792</loadEventStart>
<loadEventEnd>53814</loadEventEnd>
<domContentLoadedEventStart>21255</domContentLoadedEventStart>
<domContentLoadedEventEnd>21626</domContentLoadedEventEnd>
<lastVisualChange>42790</lastVisualChange>
<browser_name>Google Chrome</browser_name>
<browser_version>56.0.2924.87</browser_version>
<server_count>1</server_count>
<server_rtt>0</server_rtt>
<base_page_cdn>Instart Logic</base_page_cdn>
<adult_site>0</adult_site>
<fixed_viewport>1</fixed_viewport>
<score_progressive_jpeg>-1</score_progressive_jpeg>
<firstPaint>9623</firstPaint>
<docCPUms>46410.298</docCPUms>
<fullyLoadedCPUms>48578.711</fullyLoadedCPUms>
<docCPUpct>86</docCPUpct>
<fullyLoadedCPUpct>83</fullyLoadedCPUpct>
<isResponsive>-1</isResponsive>
<date>1489357746</date>
<userTime.markFormatInit>38463</userTime.markFormatInit>
<userTimes>
<markFormatInit>38463</markFormatInit>
<markUserSyncRequest>38991</markUserSyncRequest>
<markPageStart>39068</markPageStart>
<markAdRequest>39068</markAdRequest>
<markPageEnd>40368</markPageEnd>
<markUserSyncResponse>43298</markUserSyncResponse>
</userTimes>
<userTime.markUserSyncRequest>38991</userTime.markUserSyncRequest>
<userTime.markPageStart>39068</userTime.markPageStart>
<userTime.markAdRequest>39068</userTime.markAdRequest>
<userTime.markPageEnd>40368</userTime.markPageEnd>
<userTime.markUserSyncResponse>43298</userTime.markUserSyncResponse>
<userTime>43298</userTime>
<SpeedIndex>13876</SpeedIndex>
<visualComplete>21200</visualComplete>
<chromeUserTiming>
<value>
<name>fetchStart</name>
<time>1</time>
</value>
<value>
<name>unloadEventStart</name>
<time>1567</time>
</value>
<value>
<name>unloadEventEnd</name>
<time>1567</time>
</value>
<value>
<name>responseEnd</name>
<time>1643</time>
</value>
<value>
<name>firstMeaningfulPaint</name>
<time>10762</time>
</value>
<value>
<name>loadEventStart</name>
<time>53791</time>
</value>
<value>
<name>loadEventEnd</name>
<time>53813</time>
</value>
</chromeUserTiming>
<chromeUserTiming.fetchStart>1</chromeUserTiming.fetchStart>
<chromeUserTiming.unloadEventStart>1567</chromeUserTiming.unloadEventStart>
<chromeUserTiming.unloadEventEnd>1567</chromeUserTiming.unloadEventEnd>
<chromeUserTiming.responseEnd>1643</chromeUserTiming.responseEnd>
<chromeUserTiming.firstMeaningfulPaint>10762</chromeUserTiming.firstMeaningfulPaint>
<chromeUserTiming.loadEventStart>53791</chromeUserTiming.loadEventStart>
<chromeUserTiming.loadEventEnd>53813</chromeUserTiming.loadEventEnd>
<run>2</run>
<effectiveBps>72454</effectiveBps>
<effectiveBpsDoc>76419</effectiveBpsDoc>
<consoleLog>
<entry>
<source>console-api</source>
<level>debug</level>
<message>a: 0.000ms</message>
<url>https://cdn.adsafeprotected.com/sca.17.2.2.js</url>
<line>20</line>
</entry>
<entry>
<source>console-api</source>
<level>log</level>
<message>boomerang.nt: [info] This user agent supports NavigationTiming.</message>
<url>https://js.washingtonpost.com/wp-stat/rum/wprum.min.js</url>
<line>1</line>
</entry>
<entry>
<source>console-api</source>
<level>log</level>
<message>pt.fetchStart: 1489357746606</message>
<url>https://js.washingtonpost.com/wp-stat/rum/wprum.min.js</url>
<line>1</line>
</entry>
<entry>
<source>console-api</source>
<level>log</level>
<message>boomerang: [debug] Checking if we can send beacon</message>
<url>https://js.washingtonpost.com/wp-stat/rum/wprum.min.js</url>
<line>1</line>
</entry>
<entry>
<source>console-api</source>
<level>log</level>
<message>boomerang: [debug] Sending url: //rumds.wpdigital.net/metrics/?rum=%7B%22redt%22%3A0%2C%22nl%22%3A1642%2C%22dns%22%3A0%2C%22tcp%22%3A164%2C%22rest%22%3A300%2C%22domt%22%3A21624%2C%22uplt%22%3A53812%2C%22url%22%3A%22https%3A%2F%2Fwww.washingtonpost.com%2Fnews%2Fworldviews%2Fwp%2F2017%2F02%2F06%2Fbreaking-bad-fan-who-dissolved-cops-body-in-acid-is-found-dead-in-prison%2F%3Futm_term%3D.3d2095ed322a%22%2C%22site%22%3A%22www.washingtonpost.com%22%2C%22title%22%3A%22%E2%80%98Breaking%20Bad%E2%80%99%20fan%20who%20dissolved%20cop%E2%80%99s%20body%20in%20acid%20is%20found%20dead%20in%20prison%20-%20The%20Washington%20Post%22%2C%22domn%22%3A1285%2C%22jhs%22%3A15200000%2C%22fpt%22%3A1489357756.228%2C%22section%22%3A%22world%22%2C%22cntt%22%3A%22blog%22%7Dv=0.9u=https%3A%2F%2Fwww.washingtonpost.com%2Fnews%2Fworldviews%2Fwp%2F2017%2F02%2F06%2Fbreaking-bad-fan-who-dissolved-cops-body-in-acid-is-found-dead-in-prison%2F%3Futm_term%3D.3d2095ed322aif=</message>
<url>https://js.washingtonpost.com/wp-stat/rum/wprum.min.js</url>
<line>1</line>
</entry>
</consoleLog>
</firstView>
</median>
<run>
<id>1</id>
<firstView>
<tester>WIN-V9F8885QKK2-165.124.182.230</tester>
<results>
<URL>https://www.washingtonpost.com/news/worldviews/wp/2017/02/06/breaking-bad-fan-who-dissolved-cops-body-in-acid-is-found-dead-in-prison/</URL>
<loadTime>85779</loadTime>
<TTFB>1112</TTFB>
<bytesOut>222660</bytesOut>
<bytesOutDoc>216985</bytesOutDoc>
<bytesIn>3083227</bytesIn>
<bytesInDoc>3075530</bytesInDoc>
<connections>116</connections>
<requests>273</requests>
<requestsFull>273</requestsFull>
<requestsDoc>273</requestsDoc>
<responses_200>189</responses_200>
<responses_404>0</responses_404>
<responses_other>50</responses_other>
<result>0</result>
<render>611</render>
<fullyLoaded>85779</fullyLoaded>
<cached>0</cached>
<docTime>85779</docTime>
<domTime>0</domTime>
<score_cache>45</score_cache>
<score_cdn>85</score_cdn>
<score_gzip>100</score_gzip>
<score_cookies>-1</score_cookies>
<score_keep-alive>97</score_keep-alive>
<score_minify>-1</score_minify>
<score_combine>100</score_combine>
<score_compress>-1</score_compress>
<score_etags>-1</score_etags>
<gzip_total>51480</gzip_total>
<gzip_savings>0</gzip_savings>
<minify_total>0</minify_total>
<minify_savings>0</minify_savings>
<image_total>0</image_total>
<image_savings>0</image_savings>
<optimization_checked>1</optimization_checked>
<aft>0</aft>
<domElements>1288</domElements>
<pageSpeedVersion>1.9</pageSpeedVersion>
<title>&amp;lsquo;Breaking Bad&amp;rsquo; fan who dissolved cop&amp;rsquo;s body in acid is found dead in prison - The Washington Post</title>
<titleTime>3345</titleTime>
<loadEventStart>85637</loadEventStart>
<loadEventEnd>85673</loadEventEnd>
<domContentLoadedEventStart>16559</domContentLoadedEventStart>
<domContentLoadedEventEnd>16641</domContentLoadedEventEnd>
<lastVisualChange>86230</lastVisualChange>
<browser_name>Google Chrome</browser_name>
<browser_version>56.0.2924.87</browser_version>
<server_count>1</server_count>
<server_rtt>0</server_rtt>
<base_page_cdn>Instart Logic</base_page_cdn>
<adult_site>0</adult_site>
<fixed_viewport>1</fixed_viewport>
<score_progressive_jpeg>-1</score_progressive_jpeg>
<firstPaint>9181</firstPaint>
<docCPUms>58063.572</docCPUms>
<fullyLoadedCPUms>59451.981</fullyLoadedCPUms>
<docCPUpct>67</docCPUpct>
<fullyLoadedCPUpct>67</fullyLoadedCPUpct>
<isResponsive>-1</isResponsive>
<date>1489357638</date>
<userTime.markFormatInit>29988</userTime.markFormatInit>
<userTimes>
<markFormatInit>29988</markFormatInit>
<markUserSyncRequest>30104</markUserSyncRequest>
<markPageStart>30232</markPageStart>
<markAdRequest>30232</markAdRequest>
<markPageEnd>31208</markPageEnd>
<markUserSyncResponse>33757</markUserSyncResponse>
</userTimes>
<userTime.markUserSyncRequest>30104</userTime.markUserSyncRequest>
<userTime.markPageStart>30232</userTime.markPageStart>
<userTime.markAdRequest>30232</userTime.markAdRequest>
<userTime.markPageEnd>31208</userTime.markPageEnd>
<userTime.markUserSyncResponse>33757</userTime.markUserSyncResponse>
<userTime>33757</userTime>
<SpeedIndex>14403</SpeedIndex>
<visualComplete>21300</visualComplete>
<chromeUserTiming>
<value>
<name>fetchStart</name>
<time>1</time>
</value>
<value>
<name>unloadEventStart</name>
<time>2541</time>
</value>
<value>
<name>unloadEventEnd</name>
<time>2541</time>
</value>
<value>
<name>responseEnd</name>
<time>2605</time>
</value>
<value>
<name>loadEventStart</name>
<time>85637</time>
</value>
<value>
<name>loadEventEnd</name>
<time>85672</time>
</value>
<value>
<name>firstMeaningfulPaint</name>
<time>10053</time>
</value>
</chromeUserTiming>
<chromeUserTiming.fetchStart>1</chromeUserTiming.fetchStart>
<chromeUserTiming.unloadEventStart>2541</chromeUserTiming.unloadEventStart>
<chromeUserTiming.unloadEventEnd>2541</chromeUserTiming.unloadEventEnd>
<chromeUserTiming.responseEnd>2605</chromeUserTiming.responseEnd>
<chromeUserTiming.loadEventStart>85637</chromeUserTiming.loadEventStart>
<chromeUserTiming.loadEventEnd>85672</chromeUserTiming.loadEventEnd>
<chromeUserTiming.firstMeaningfulPaint>10053</chromeUserTiming.firstMeaningfulPaint>
<run>1</run>
<effectiveBps>36415</effectiveBps>
<effectiveBpsDoc>36325</effectiveBpsDoc>
</results>
<pages>
<details>http://104.198.155.24/details.php?test=170312_FT_febf26e2b0f2dfc23c02ce6f9f77f935&amp;run=1</details>
<checklist>http://104.198.155.24/performance_optimization.php?test=170312_FT_febf26e2b0f2dfc23c02ce6f9f77f935&amp;run=1</checklist>
<breakdown>http://104.198.155.24/breakdown.php?test=170312_FT_febf26e2b0f2dfc23c02ce6f9f77f935&amp;run=1</breakdown>
<domains>http://104.198.155.24/domains.php?test=170312_FT_febf26e2b0f2dfc23c02ce6f9f77f935&amp;run=1</domains>
<screenShot>http://104.198.155.24/screen_shot.php?test=170312_FT_febf26e2b0f2dfc23c02ce6f9f77f935&amp;run=1</screenShot>
</pages>
<thumbnails>
<waterfall>http://104.198.155.24/result/170312_FT_febf26e2b0f2dfc23c02ce6f9f77f935/1_waterfall_thumb.png</waterfall>
<checklist>http://104.198.155.24/result/170312_FT_febf26e2b0f2dfc23c02ce6f9f77f935/1_optimization_thumb.png</checklist>
<screenShot>http://104.198.155.24/result/170312_FT_febf26e2b0f2dfc23c02ce6f9f77f935/1_screen_thumb.jpg</screenShot>
</thumbnails>
<images>
<waterfall>http://104.198.155.24/results/17/03/12/FT/febf26e2b0f2dfc23c02ce6f9f77f935/1_waterfall.png</waterfall>
<connectionView>http://104.198.155.24/results/17/03/12/FT/febf26e2b0f2dfc23c02ce6f9f77f935/1_connection.png</connectionView>
<checklist>http://104.198.155.24/results/17/03/12/FT/febf26e2b0f2dfc23c02ce6f9f77f935/1_optimization.png</checklist>
<screenShot>http://104.198.155.24/getfile.php?test=170312_FT_febf26e2b0f2dfc23c02ce6f9f77f935&amp;file=1_screen.jpg</screenShot>
</images>
<rawData><headers>http://104.198.155.24/results/17/03/12/FT/febf26e2b0f2dfc23c02ce6f9f77f935/1_report.txt</headers>
<pageData>http://104.198.155.24/results/17/03/12/FT/febf26e2b0f2dfc23c02ce6f9f77f935/1_IEWPG.txt</pageData>
<requestsData>http://104.198.155.24/results/17/03/12/FT/febf26e2b0f2dfc23c02ce6f9f77f935/1_IEWTR.txt</requestsData>
<utilization>http://104.198.155.24/results/17/03/12/FT/febf26e2b0f2dfc23c02ce6f9f77f935/1_progress.csv</utilization>
</rawData>
<videoFrames>
<frame>
<time>0</time>
<image>http://104.198.155.24/getfile.php?test=170312_FT_febf26e2b0f2dfc23c02ce6f9f77f935&amp;video=video_1&amp;file=frame_0000.jpg</image>
<VisuallyComplete>0</VisuallyComplete>
</frame>
<frame>
<time>600</time>
<image>http://104.198.155.24/getfile.php?test=170312_FT_febf26e2b0f2dfc23c02ce6f9f77f935&amp;video=video_1&amp;file=frame_0006.jpg</image>
<VisuallyComplete>2</VisuallyComplete>
</frame>
<frame>
<time>3900</time>
<image>http://104.198.155.24/getfile.php?test=170312_FT_febf26e2b0f2dfc23c02ce6f9f77f935&amp;video=video_1&amp;file=frame_0039.jpg</image>
<VisuallyComplete>2</VisuallyComplete>
</frame>
<frame>
<time>4100</time>
<image>http://104.198.155.24/getfile.php?test=170312_FT_febf26e2b0f2dfc23c02ce6f9f77f935&amp;video=video_1&amp;file=frame_0041.jpg</image>
<VisuallyComplete>0</VisuallyComplete>
</frame>
<frame>
<time>4800</time>
<image>http://104.198.155.24/getfile.php?test=170312_FT_febf26e2b0f2dfc23c02ce6f9f77f935&amp;video=video_1&amp;file=frame_0048.jpg</image>
<VisuallyComplete>2</VisuallyComplete>
</frame>
<frame>
<time>5500</time>
<image>http://104.198.155.24/getfile.php?test=170312_FT_febf26e2b0f2dfc23c02ce6f9f77f935&amp;video=video_1&amp;file=frame_0055.jpg</image>
<VisuallyComplete>1</VisuallyComplete>
</frame>
<frame>
<time>5600</time>
<image>http://104.198.155.24/getfile.php?test=170312_FT_febf26e2b0f2dfc23c02ce6f9f77f935&amp;video=video_1&amp;file=frame_0056.jpg</image>
<VisuallyComplete>0</VisuallyComplete>
</frame>
<frame>
<time>8100</time>
<image>http://104.198.155.24/getfile.php?test=170312_FT_febf26e2b0f2dfc23c02ce6f9f77f935&amp;video=video_1&amp;file=frame_0081.jpg</image>
<VisuallyComplete>2</VisuallyComplete>
</frame>
<frame>
<time>8800</time>
<image>http://104.198.155.24/getfile.php?test=170312_FT_febf26e2b0f2dfc23c02ce6f9f77f935&amp;video=video_1&amp;file=frame_0088.jpg</image>
<VisuallyComplete>1</VisuallyComplete>
</frame>
<frame>
<time>8900</time>
<image>http://104.198.155.24/getfile.php?test=170312_FT_febf26e2b0f2dfc23c02ce6f9f77f935&amp;video=video_1&amp;file=frame_0089.jpg</image>
<VisuallyComplete>0</VisuallyComplete>
</frame>
<frame>
<time>11600</time>
<image>http://104.198.155.24/getfile.php?test=170312_FT_febf26e2b0f2dfc23c02ce6f9f77f935&amp;video=video_1&amp;file=frame_0116.jpg</image>
<VisuallyComplete>2</VisuallyComplete>
</frame>
<frame>
<time>12900</time>
<image>http://104.198.155.24/getfile.php?test=170312_FT_febf26e2b0f2dfc23c02ce6f9f77f935&amp;video=video_1&amp;file=frame_0129.jpg</image>
<VisuallyComplete>1</VisuallyComplete>
</frame>
<frame>
<time>13000</time>
<image>http://104.198.155.24/getfile.php?test=170312_FT_febf26e2b0f2dfc23c02ce6f9f77f935&amp;video=video_1&amp;file=frame_0130.jpg</image>
<VisuallyComplete>0</VisuallyComplete>
</frame>
<frame>
<time>13700</time>
<image>http://104.198.155.24/getfile.php?test=170312_FT_febf26e2b0f2dfc23c02ce6f9f77f935&amp;video=video_1&amp;file=frame_0137.jpg</image>
<VisuallyComplete>28</VisuallyComplete>
</frame>
<frame>
<time>13900</time>
<image>http://104.198.155.24/getfile.php?test=170312_FT_febf26e2b0f2dfc23c02ce6f9f77f935&amp;video=video_1&amp;file=frame_0139.jpg</image>
<VisuallyComplete>28</VisuallyComplete>
</frame>
<frame>
<time>14700</time>
<image>http://104.198.155.24/getfile.php?test=170312_FT_febf26e2b0f2dfc23c02ce6f9f77f935&amp;video=video_1&amp;file=frame_0147.jpg</image>
<VisuallyComplete>99</VisuallyComplete>
</frame>
<frame>
<time>16300</time>
<image>http://104.198.155.24/getfile.php?test=170312_FT_febf26e2b0f2dfc23c02ce6f9f77f935&amp;video=video_1&amp;file=frame_0163.jpg</image>
<VisuallyComplete>99</VisuallyComplete>
</frame>
<frame>
<time>17900</time>
<image>http://104.198.155.24/getfile.php?test=170312_FT_febf26e2b0f2dfc23c02ce6f9f77f935&amp;video=video_1&amp;file=frame_0179.jpg</image>
<VisuallyComplete>99</VisuallyComplete>
</frame>
<frame>
<time>21300</time>
<image>http://104.198.155.24/getfile.php?test=170312_FT_febf26e2b0f2dfc23c02ce6f9f77f935&amp;video=video_1&amp;file=frame_0213.jpg</image>
<VisuallyComplete>100</VisuallyComplete>
</frame>
<frame>
<time>84000</time>
<image>http://104.198.155.24/getfile.php?test=170312_FT_febf26e2b0f2dfc23c02ce6f9f77f935&amp;video=video_1&amp;file=frame_0840.jpg</image>
<VisuallyComplete>98</VisuallyComplete>
</frame>
<frame>
<time>86200</time>
<image>http://104.198.155.24/getfile.php?test=170312_FT_febf26e2b0f2dfc23c02ce6f9f77f935&amp;video=video_1&amp;file=frame_0862.jpg</image>
<VisuallyComplete>100</VisuallyComplete>
</frame>
</videoFrames>
<consoleLog>
<entry>
<source>console-api</source>
<level>log</level>
<message>boomerang.nt: [info] This user agent supports NavigationTiming.</message>
<url>https://js.washingtonpost.com/wp-stat/rum/wprum.min.js</url>
<line>1</line>
</entry>
<entry>
<source>console-api</source>
<level>log</level>
<message>pt.fetchStart: 1489357639083</message>
<url>https://js.washingtonpost.com/wp-stat/rum/wprum.min.js</url>
<line>1</line>
</entry>
<entry>
<source>console-api</source>
<level>log</level>
<message>boomerang: [debug] Checking if we can send beacon</message>
<url>https://js.washingtonpost.com/wp-stat/rum/wprum.min.js</url>
<line>1</line>
</entry>
<entry>
<source>console-api</source>
<level>log</level>
<message>boomerang: [debug] Sending url: //rumds.wpdigital.net/metrics/?rum=%7B%22redt%22%3A0%2C%22nl%22%3A2605%2C%22dns%22%3A0%2C%22tcp%22%3A267%2C%22rest%22%3A916%2C%22domt%22%3A16640%2C%22uplt%22%3A85672%2C%22url%22%3A%22https%3A%2F%2Fwww.washingtonpost.com%2Fnews%2Fworldviews%2Fwp%2F2017%2F02%2F06%2Fbreaking-bad-fan-who-dissolved-cops-body-in-acid-is-found-dead-in-prison%2F%22%2C%22site%22%3A%22www.washingtonpost.com%22%2C%22title%22%3A%22%E2%80%98Breaking%20Bad%E2%80%99%20fan%20who%20dissolved%20cop%E2%80%99s%20body%20in%20acid%20is%20found%20dead%20in%20prison%20-%20The%20Washington%20Post%22%2C%22domn%22%3A1289%2C%22jhs%22%3A16100000%2C%22fpt%22%3A1489357648.264%2C%22section%22%3A%22world%22%2C%22cntt%22%3A%22blog%22%7Dv=0.9u=https%3A%2F%2Fwww.washingtonpost.com%2Fnews%2Fworldviews%2Fwp%2F2017%2F02%2F06%2Fbreaking-bad-fan-who-dissolved-cops-body-in-acid-is-found-dead-in-prison%2Fif=</message>
<url>https://js.washingtonpost.com/wp-stat/rum/wprum.min.js</url>
<line>1</line>
</entry>
</consoleLog>
</firstView>
</run>
<run>
<id>2</id>
<firstView>
<tester>WIN-V9F8885QKK2-165.124.182.230</tester>
<results>
<URL>https://www.washingtonpost.com/news/worldviews/wp/2017/02/06/breaking-bad-fan-who-dissolved-cops-body-in-acid-is-found-dead-in-prison/</URL>
<loadTime>52405</loadTime>
<TTFB>626</TTFB>
<bytesOut>270123</bytesOut>
<bytesOutDoc>264385</bytesOutDoc>
<bytesIn>3964147</bytesIn>
<bytesInDoc>3956910</bytesInDoc>
<connections>133</connections>
<requests>308</requests>
<requestsFull>308</requestsFull>
<requestsDoc>305</requestsDoc>
<responses_200>220</responses_200>
<responses_404>0</responses_404>
<responses_other>52</responses_other>
<result>0</result>
<render>1600</render>
<fullyLoaded>55338</fullyLoaded>
<cached>0</cached>
<docTime>52405</docTime>
<domTime>0</domTime>
<score_cache>37</score_cache>
<score_cdn>67</score_cdn>
<score_gzip>100</score_gzip>
<score_cookies>-1</score_cookies>
<score_keep-alive>98</score_keep-alive>
<score_minify>-1</score_minify>
<score_combine>100</score_combine>
<score_compress>-1</score_compress>
<score_etags>-1</score_etags>
<gzip_total>56644</gzip_total>
<gzip_savings>0</gzip_savings>
<minify_total>0</minify_total>
<minify_savings>0</minify_savings>
<image_total>0</image_total>
<image_savings>0</image_savings>
<optimization_checked>1</optimization_checked>
<aft>0</aft>
<domElements>1285</domElements>
<pageSpeedVersion>1.9</pageSpeedVersion>
<title>&amp;lsquo;Breaking Bad&amp;rsquo; fan who dissolved cop&amp;rsquo;s body in acid is found dead in prison - The Washington Post</title>
<titleTime>709</titleTime>
<loadEventStart>53792</loadEventStart>
<loadEventEnd>53814</loadEventEnd>
<domContentLoadedEventStart>21255</domContentLoadedEventStart>
<domContentLoadedEventEnd>21626</domContentLoadedEventEnd>
<lastVisualChange>42790</lastVisualChange>
<browser_name>Google Chrome</browser_name>
<browser_version>56.0.2924.87</browser_version>
<server_count>1</server_count>
<server_rtt>0</server_rtt>
<base_page_cdn>Instart Logic</base_page_cdn>
<adult_site>0</adult_site>
<fixed_viewport>1</fixed_viewport>
<score_progressive_jpeg>-1</score_progressive_jpeg>
<firstPaint>9623</firstPaint>
<docCPUms>46410.298</docCPUms>
<fullyLoadedCPUms>48578.711</fullyLoadedCPUms>
<docCPUpct>86</docCPUpct>
<fullyLoadedCPUpct>83</fullyLoadedCPUpct>
<isResponsive>-1</isResponsive>
<date>1489357746</date>
<userTime.markFormatInit>38463</userTime.markFormatInit>
<userTimes>
<markFormatInit>38463</markFormatInit>
<markUserSyncRequest>38991</markUserSyncRequest>
<markPageStart>39068</markPageStart>
<markAdRequest>39068</markAdRequest>
<markPageEnd>40368</markPageEnd>
<markUserSyncResponse>43298</markUserSyncResponse>
</userTimes>
<userTime.markUserSyncRequest>38991</userTime.markUserSyncRequest>
<userTime.markPageStart>39068</userTime.markPageStart>
<userTime.markAdRequest>39068</userTime.markAdRequest>
<userTime.markPageEnd>40368</userTime.markPageEnd>
<userTime.markUserSyncResponse>43298</userTime.markUserSyncResponse>
<userTime>43298</userTime>
<SpeedIndex>13876</SpeedIndex>
<visualComplete>21200</visualComplete>
<chromeUserTiming>
<value>
<name>fetchStart</name>
<time>1</time>
</value>
<value>
<name>unloadEventStart</name>
<time>1567</time>
</value>
<value>
<name>unloadEventEnd</name>
<time>1567</time>
</value>
<value>
<name>responseEnd</name>
<time>1643</time>
</value>
<value>
<name>firstMeaningfulPaint</name>
<time>10762</time>
</value>
<value>
<name>loadEventStart</name>
<time>53791</time>
</value>
<value>
<name>loadEventEnd</name>
<time>53813</time>
</value>
</chromeUserTiming>
<chromeUserTiming.fetchStart>1</chromeUserTiming.fetchStart>
<chromeUserTiming.unloadEventStart>1567</chromeUserTiming.unloadEventStart>
<chromeUserTiming.unloadEventEnd>1567</chromeUserTiming.unloadEventEnd>
<chromeUserTiming.responseEnd>1643</chromeUserTiming.responseEnd>
<chromeUserTiming.firstMeaningfulPaint>10762</chromeUserTiming.firstMeaningfulPaint>
<chromeUserTiming.loadEventStart>53791</chromeUserTiming.loadEventStart>
<chromeUserTiming.loadEventEnd>53813</chromeUserTiming.loadEventEnd>
<run>2</run>
<effectiveBps>72454</effectiveBps>
<effectiveBpsDoc>76419</effectiveBpsDoc>
</results>
<pages>
<details>http://104.198.155.24/details.php?test=170312_FT_febf26e2b0f2dfc23c02ce6f9f77f935&amp;run=2</details>
<checklist>http://104.198.155.24/performance_optimization.php?test=170312_FT_febf26e2b0f2dfc23c02ce6f9f77f935&amp;run=2</checklist>
<breakdown>http://104.198.155.24/breakdown.php?test=170312_FT_febf26e2b0f2dfc23c02ce6f9f77f935&amp;run=2</breakdown>
<domains>http://104.198.155.24/domains.php?test=170312_FT_febf26e2b0f2dfc23c02ce6f9f77f935&amp;run=2</domains>
<screenShot>http://104.198.155.24/screen_shot.php?test=170312_FT_febf26e2b0f2dfc23c02ce6f9f77f935&amp;run=2</screenShot>
</pages>
<thumbnails>
<waterfall>http://104.198.155.24/result/170312_FT_febf26e2b0f2dfc23c02ce6f9f77f935/2_waterfall_thumb.png</waterfall>
<checklist>http://104.198.155.24/result/170312_FT_febf26e2b0f2dfc23c02ce6f9f77f935/2_optimization_thumb.png</checklist>
<screenShot>http://104.198.155.24/result/170312_FT_febf26e2b0f2dfc23c02ce6f9f77f935/2_screen_thumb.jpg</screenShot>
</thumbnails>
<images>
<waterfall>http://104.198.155.24/results/17/03/12/FT/febf26e2b0f2dfc23c02ce6f9f77f935/2_waterfall.png</waterfall>
<connectionView>http://104.198.155.24/results/17/03/12/FT/febf26e2b0f2dfc23c02ce6f9f77f935/2_connection.png</connectionView>
<checklist>http://104.198.155.24/results/17/03/12/FT/febf26e2b0f2dfc23c02ce6f9f77f935/2_optimization.png</checklist>
<screenShot>http://104.198.155.24/getfile.php?test=170312_FT_febf26e2b0f2dfc23c02ce6f9f77f935&amp;file=2_screen.jpg</screenShot>
</images>
<rawData><headers>http://104.198.155.24/results/17/03/12/FT/febf26e2b0f2dfc23c02ce6f9f77f935/2_report.txt</headers>
<pageData>http://104.198.155.24/results/17/03/12/FT/febf26e2b0f2dfc23c02ce6f9f77f935/2_IEWPG.txt</pageData>
<requestsData>http://104.198.155.24/results/17/03/12/FT/febf26e2b0f2dfc23c02ce6f9f77f935/2_IEWTR.txt</requestsData>
<utilization>http://104.198.155.24/results/17/03/12/FT/febf26e2b0f2dfc23c02ce6f9f77f935/2_progress.csv</utilization>
</rawData>
<videoFrames>
<frame>
<time>0</time>
<image>http://104.198.155.24/getfile.php?test=170312_FT_febf26e2b0f2dfc23c02ce6f9f77f935&amp;video=video_2&amp;file=frame_0000.jpg</image>
<VisuallyComplete>0</VisuallyComplete>
</frame>
<frame>
<time>1600</time>
<image>http://104.198.155.24/getfile.php?test=170312_FT_febf26e2b0f2dfc23c02ce6f9f77f935&amp;video=video_2&amp;file=frame_0016.jpg</image>
<VisuallyComplete>1</VisuallyComplete>
</frame>
<frame>
<time>1800</time>
<image>http://104.198.155.24/getfile.php?test=170312_FT_febf26e2b0f2dfc23c02ce6f9f77f935&amp;video=video_2&amp;file=frame_0018.jpg</image>
<VisuallyComplete>0</VisuallyComplete>
</frame>
<frame>
<time>7000</time>
<image>http://104.198.155.24/getfile.php?test=170312_FT_febf26e2b0f2dfc23c02ce6f9f77f935&amp;video=video_2&amp;file=frame_0070.jpg</image>
<VisuallyComplete>2</VisuallyComplete>
</frame>
<frame>
<time>7900</time>
<image>http://104.198.155.24/getfile.php?test=170312_FT_febf26e2b0f2dfc23c02ce6f9f77f935&amp;video=video_2&amp;file=frame_0079.jpg</image>
<VisuallyComplete>1</VisuallyComplete>
</frame>
<frame>
<time>8100</time>
<image>http://104.198.155.24/getfile.php?test=170312_FT_febf26e2b0f2dfc23c02ce6f9f77f935&amp;video=video_2&amp;file=frame_0081.jpg</image>
<VisuallyComplete>0</VisuallyComplete>
</frame>
<frame>
<time>9200</time>
<image>http://104.198.155.24/getfile.php?test=170312_FT_febf26e2b0f2dfc23c02ce6f9f77f935&amp;video=video_2&amp;file=frame_0092.jpg</image>
<VisuallyComplete>2</VisuallyComplete>
</frame>
<frame>
<time>11000</time>
<image>http://104.198.155.24/getfile.php?test=170312_FT_febf26e2b0f2dfc23c02ce6f9f77f935&amp;video=video_2&amp;file=frame_0110.jpg</image>
<VisuallyComplete>28</VisuallyComplete>
</frame>
<frame>
<time>11300</time>
<image>http://104.198.155.24/getfile.php?test=170312_FT_febf26e2b0f2dfc23c02ce6f9f77f935&amp;video=video_2&amp;file=frame_0113.jpg</image>
<VisuallyComplete>28</VisuallyComplete>
</frame>
<frame>
<time>11400</time>
<image>http://104.198.155.24/getfile.php?test=170312_FT_febf26e2b0f2dfc23c02ce6f9f77f935&amp;video=video_2&amp;file=frame_0114.jpg</image>
<VisuallyComplete>28</VisuallyComplete>
</frame>
<frame>
<time>13600</time>
<image>http://104.198.155.24/getfile.php?test=170312_FT_febf26e2b0f2dfc23c02ce6f9f77f935&amp;video=video_2&amp;file=frame_0136.jpg</image>
<VisuallyComplete>28</VisuallyComplete>
</frame>
<frame>
<time>14600</time>
<image>http://104.198.155.24/getfile.php?test=170312_FT_febf26e2b0f2dfc23c02ce6f9f77f935&amp;video=video_2&amp;file=frame_0146.jpg</image>
<VisuallyComplete>99</VisuallyComplete>
</frame>
<frame>
<time>15100</time>
<image>http://104.198.155.24/getfile.php?test=170312_FT_febf26e2b0f2dfc23c02ce6f9f77f935&amp;video=video_2&amp;file=frame_0151.jpg</image>
<VisuallyComplete>99</VisuallyComplete>
</frame>
<frame>
<time>15300</time>
<image>http://104.198.155.24/getfile.php?test=170312_FT_febf26e2b0f2dfc23c02ce6f9f77f935&amp;video=video_2&amp;file=frame_0153.jpg</image>
<VisuallyComplete>99</VisuallyComplete>
</frame>
<frame>
<time>15400</time>
<image>http://104.198.155.24/getfile.php?test=170312_FT_febf26e2b0f2dfc23c02ce6f9f77f935&amp;video=video_2&amp;file=frame_0154.jpg</image>
<VisuallyComplete>99</VisuallyComplete>
</frame>
<frame>
<time>18700</time>
<image>http://104.198.155.24/getfile.php?test=170312_FT_febf26e2b0f2dfc23c02ce6f9f77f935&amp;video=video_2&amp;file=frame_0187.jpg</image>
<VisuallyComplete>99</VisuallyComplete>
</frame>
<frame>
<time>19800</time>
<image>http://104.198.155.24/getfile.php?test=170312_FT_febf26e2b0f2dfc23c02ce6f9f77f935&amp;video=video_2&amp;file=frame_0198.jpg</image>
<VisuallyComplete>99</VisuallyComplete>
</frame>
<frame>
<time>19900</time>
<image>http://104.198.155.24/getfile.php?test=170312_FT_febf26e2b0f2dfc23c02ce6f9f77f935&amp;video=video_2&amp;file=frame_0199.jpg</image>
<VisuallyComplete>99</VisuallyComplete>
</frame>
<frame>
<time>20500</time>
<image>http://104.198.155.24/getfile.php?test=170312_FT_febf26e2b0f2dfc23c02ce6f9f77f935&amp;video=video_2&amp;file=frame_0205.jpg</image>
<VisuallyComplete>99</VisuallyComplete>
</frame>
<frame>
<time>21200</time>
<image>http://104.198.155.24/getfile.php?test=170312_FT_febf26e2b0f2dfc23c02ce6f9f77f935&amp;video=video_2&amp;file=frame_0212.jpg</image>
<VisuallyComplete>100</VisuallyComplete>
</frame>
<frame>
<time>26200</time>
<image>http://104.198.155.24/getfile.php?test=170312_FT_febf26e2b0f2dfc23c02ce6f9f77f935&amp;video=video_2&amp;file=frame_0262.jpg</image>
<VisuallyComplete>98</VisuallyComplete>
</frame>
<frame>
<time>35000</time>
<image>http://104.198.155.24/getfile.php?test=170312_FT_febf26e2b0f2dfc23c02ce6f9f77f935&amp;video=video_2&amp;file=frame_0350.jpg</image>
<VisuallyComplete>100</VisuallyComplete>
</frame>
<frame>
<time>37800</time>
<image>http://104.198.155.24/getfile.php?test=170312_FT_febf26e2b0f2dfc23c02ce6f9f77f935&amp;video=video_2&amp;file=frame_0378.jpg</image>
<VisuallyComplete>98</VisuallyComplete>
</frame>
<frame>
<time>42800</time>
<image>http://104.198.155.24/getfile.php?test=170312_FT_febf26e2b0f2dfc23c02ce6f9f77f935&amp;video=video_2&amp;file=frame_0428.jpg</image>
<VisuallyComplete>100</VisuallyComplete>
</frame>
</videoFrames>
<consoleLog>
<entry>
<source>console-api</source>
<level>debug</level>
<message>a: 0.000ms</message>
<url>https://cdn.adsafeprotected.com/sca.17.2.2.js</url>
<line>20</line>
</entry>
<entry>
<source>console-api</source>
<level>log</level>
<message>boomerang.nt: [info] This user agent supports NavigationTiming.</message>
<url>https://js.washingtonpost.com/wp-stat/rum/wprum.min.js</url>
<line>1</line>
</entry>
<entry>
<source>console-api</source>
<level>log</level>
<message>pt.fetchStart: 1489357746606</message>
<url>https://js.washingtonpost.com/wp-stat/rum/wprum.min.js</url>
<line>1</line>
</entry>
<entry>
<source>console-api</source>
<level>log</level>
<message>boomerang: [debug] Checking if we can send beacon</message>
<url>https://js.washingtonpost.com/wp-stat/rum/wprum.min.js</url>
<line>1</line>
</entry>
<entry>
<source>console-api</source>
<level>log</level>
<message>boomerang: [debug] Sending url: //rumds.wpdigital.net/metrics/?rum=%7B%22redt%22%3A0%2C%22nl%22%3A1642%2C%22dns%22%3A0%2C%22tcp%22%3A164%2C%22rest%22%3A300%2C%22domt%22%3A21624%2C%22uplt%22%3A53812%2C%22url%22%3A%22https%3A%2F%2Fwww.washingtonpost.com%2Fnews%2Fworldviews%2Fwp%2F2017%2F02%2F06%2Fbreaking-bad-fan-who-dissolved-cops-body-in-acid-is-found-dead-in-prison%2F%3Futm_term%3D.3d2095ed322a%22%2C%22site%22%3A%22www.washingtonpost.com%22%2C%22title%22%3A%22%E2%80%98Breaking%20Bad%E2%80%99%20fan%20who%20dissolved%20cop%E2%80%99s%20body%20in%20acid%20is%20found%20dead%20in%20prison%20-%20The%20Washington%20Post%22%2C%22domn%22%3A1285%2C%22jhs%22%3A15200000%2C%22fpt%22%3A1489357756.228%2C%22section%22%3A%22world%22%2C%22cntt%22%3A%22blog%22%7Dv=0.9u=https%3A%2F%2Fwww.washingtonpost.com%2Fnews%2Fworldviews%2Fwp%2F2017%2F02%2F06%2Fbreaking-bad-fan-who-dissolved-cops-body-in-acid-is-found-dead-in-prison%2F%3Futm_term%3D.3d2095ed322aif=</message>
<url>https://js.washingtonpost.com/wp-stat/rum/wprum.min.js</url>
<line>1</line>
</entry>
</consoleLog>
</firstView>
</run>
</data>
</response>