<?xml version="1.0" encoding="utf-8"?><response>
<statusCode>200</statusCode>
<statusText>Ok</statusText>
<data>
<testId>170220_MB_402967d9c046a02313f44041baa286b8</testId>
<summary>http://104.198.155.24/results.php?test=170220_MB_402967d9c046a02313f44041baa286b8</summary>
<testUrl>https://www.washingtonpost.com/news/where-we-live/wp/2017/02/09/colonial-style-alexandria-mansion-with-four-ovens-lists-for-2-095-million/</testUrl>
<location>Alex2:Chrome</location>
<from>Alex - &lt;b&gt;Chrome&lt;/b&gt; - &lt;b&gt;custom&lt;/b&gt;</from>
<connectivity>custom</connectivity>
<bwDown>1500</bwDown>
<bwUp>384</bwUp>
<latency>50</latency>
<plr>0</plr>
<mobile>0</mobile>
<completed>Mon, 20 Feb 2017 10:05:54 +0000</completed>
<tester>WIN-V9F8885QKK2-98.220.232.152</tester>
<testerDNS>172.16.125.2</testerDNS>
<runs>1</runs>
<successfulFVRuns>1</successfulFVRuns>
<average>
<firstView>
<loadTime>32794</loadTime>
<TTFB>606</TTFB>
<bytesOut>208119</bytesOut>
<bytesOutDoc>192845</bytesOutDoc>
<bytesIn>3016976</bytesIn>
<bytesInDoc>2924156</bytesInDoc>
<connections>99</connections>
<requests>239</requests>
<requestsFull>239</requestsFull>
<requestsDoc>233</requestsDoc>
<responses_200>155</responses_200>
<responses_404>0</responses_404>
<responses_other>54</responses_other>
<result>0</result>
<render>433</render>
<fullyLoaded>35569</fullyLoaded>
<cached>0</cached>
<docTime>32794</docTime>
<domTime>0</domTime>
<score_cache>42</score_cache>
<score_cdn>86</score_cdn>
<score_gzip>100</score_gzip>
<score_cookies>-1</score_cookies>
<score_keep-alive>98</score_keep-alive>
<score_minify>-1</score_minify>
<score_combine>100</score_combine>
<score_compress>-1</score_compress>
<score_etags>-1</score_etags>
<gzip_total>44767</gzip_total>
<gzip_savings>0</gzip_savings>
<minify_total>0</minify_total>
<minify_savings>0</minify_savings>
<image_total>0</image_total>
<image_savings>0</image_savings>
<optimization_checked>1</optimization_checked>
<aft>0</aft>
<domElements>1266</domElements>
<pageSpeedVersion>2</pageSpeedVersion>
<titleTime>1685</titleTime>
<loadEventStart>32773</loadEventStart>
<loadEventEnd>32785</loadEventEnd>
<domContentLoadedEventStart>9822</domContentLoadedEventStart>
<domContentLoadedEventEnd>9877</domContentLoadedEventEnd>
<lastVisualChange>33421</lastVisualChange>
<server_count>1</server_count>
<server_rtt>0</server_rtt>
<adult_site>0</adult_site>
<fixed_viewport>1</fixed_viewport>
<score_progressive_jpeg>-1</score_progressive_jpeg>
<firstPaint>7061</firstPaint>
<docCPUms>19204</docCPUms>
<fullyLoadedCPUms>20967</fullyLoadedCPUms>
<docCPUpct>58</docCPUpct>
<fullyLoadedCPUpct>53</fullyLoadedCPUpct>
<isResponsive>-1</isResponsive>
<date>1487585104</date>
<CSI.v>3</CSI.v>
<CSI.srt>1567</CSI.srt>
<CSI.tbsrt>23628</CSI.tbsrt>
<CSI.tran>15</CSI.tran>
<CSI.npn>1</CSI.npn>
<CSI.vrg>108</CSI.vrg>
<CSI.ad_render_period>1</CSI.ad_render_period>
<SpeedIndex>6942</SpeedIndex>
<visualComplete>17200</visualComplete>
<chromeUserTiming.fetchStart>0</chromeUserTiming.fetchStart>
<chromeUserTiming.unloadEventStart>1570</chromeUserTiming.unloadEventStart>
<chromeUserTiming.unloadEventEnd>1570</chromeUserTiming.unloadEventEnd>
<chromeUserTiming.responseEnd>1641</chromeUserTiming.responseEnd>
<chromeUserTiming.loadEventStart>32772</chromeUserTiming.loadEventStart>
<chromeUserTiming.loadEventEnd>32785</chromeUserTiming.loadEventEnd>
<chromeUserTiming.firstMeaningfulPaint>7060</chromeUserTiming.firstMeaningfulPaint>
<run>1</run>
<effectiveBps>86290</effectiveBps>
<effectiveBpsDoc>90846</effectiveBpsDoc>
<avgRun>1</avgRun>
</firstView>
</average>
<standardDeviation>
<firstView>
<loadTime>0</loadTime>
<TTFB>0</TTFB>
<bytesOut>0</bytesOut>
<bytesOutDoc>0</bytesOutDoc>
<bytesIn>0</bytesIn>
<bytesInDoc>0</bytesInDoc>
<connections>0</connections>
<requests>0</requests>
<requestsFull>0</requestsFull>
<requestsDoc>0</requestsDoc>
<responses_200>0</responses_200>
<responses_404>0</responses_404>
<responses_other>0</responses_other>
<result>0</result>
<render>0</render>
<fullyLoaded>0</fullyLoaded>
<cached>0</cached>
<docTime>0</docTime>
<domTime>0</domTime>
<score_cache>0</score_cache>
<score_cdn>0</score_cdn>
<score_gzip>0</score_gzip>
<score_cookies>0</score_cookies>
<score_keep-alive>0</score_keep-alive>
<score_minify>0</score_minify>
<score_combine>0</score_combine>
<score_compress>0</score_compress>
<score_etags>0</score_etags>
<gzip_total>0</gzip_total>
<gzip_savings>0</gzip_savings>
<minify_total>0</minify_total>
<minify_savings>0</minify_savings>
<image_total>0</image_total>
<image_savings>0</image_savings>
<optimization_checked>0</optimization_checked>
<aft>0</aft>
<domElements>0</domElements>
<pageSpeedVersion>0</pageSpeedVersion>
<titleTime>0</titleTime>
<loadEventStart>0</loadEventStart>
<loadEventEnd>0</loadEventEnd>
<domContentLoadedEventStart>0</domContentLoadedEventStart>
<domContentLoadedEventEnd>0</domContentLoadedEventEnd>
<lastVisualChange>0</lastVisualChange>
<server_count>0</server_count>
<server_rtt>0</server_rtt>
<adult_site>0</adult_site>
<fixed_viewport>0</fixed_viewport>
<score_progressive_jpeg>0</score_progressive_jpeg>
<firstPaint>0</firstPaint>
<docCPUms>0</docCPUms>
<fullyLoadedCPUms>0</fullyLoadedCPUms>
<docCPUpct>0</docCPUpct>
<fullyLoadedCPUpct>0</fullyLoadedCPUpct>
<isResponsive>0</isResponsive>
<date>0</date>
<CSI.v>0</CSI.v>
<CSI.srt>0</CSI.srt>
<CSI.tbsrt>0</CSI.tbsrt>
<CSI.tran>0</CSI.tran>
<CSI.npn>0</CSI.npn>
<CSI.vrg>0</CSI.vrg>
<CSI.ad_render_period>0</CSI.ad_render_period>
<SpeedIndex>0</SpeedIndex>
<visualComplete>0</visualComplete>
<chromeUserTiming.fetchStart>0</chromeUserTiming.fetchStart>
<chromeUserTiming.unloadEventStart>0</chromeUserTiming.unloadEventStart>
<chromeUserTiming.unloadEventEnd>0</chromeUserTiming.unloadEventEnd>
<chromeUserTiming.responseEnd>0</chromeUserTiming.responseEnd>
<chromeUserTiming.loadEventStart>0</chromeUserTiming.loadEventStart>
<chromeUserTiming.loadEventEnd>0</chromeUserTiming.loadEventEnd>
<chromeUserTiming.firstMeaningfulPaint>0</chromeUserTiming.firstMeaningfulPaint>
<run>0</run>
<effectiveBps>0</effectiveBps>
<effectiveBpsDoc>0</effectiveBpsDoc>
<avgRun/>
</firstView>
</standardDeviation>
<median>
<firstView>
<run>1</run>
<tester>WIN-V9F8885QKK2-98.220.232.152</tester>
<URL>https://www.washingtonpost.com/news/where-we-live/wp/2017/02/09/colonial-style-alexandria-mansion-with-four-ovens-lists-for-2-095-million/</URL>
<loadTime>32794</loadTime>
<TTFB>606</TTFB>
<bytesOut>208119</bytesOut>
<bytesOutDoc>192845</bytesOutDoc>
<bytesIn>3016976</bytesIn>
<bytesInDoc>2924156</bytesInDoc>
<connections>99</connections>
<requests>239</requests>
<requestsFull>239</requestsFull>
<requestsDoc>233</requestsDoc>
<responses_200>155</responses_200>
<responses_404>0</responses_404>
<responses_other>54</responses_other>
<result>0</result>
<render>433</render>
<fullyLoaded>35569</fullyLoaded>
<cached>0</cached>
<docTime>32794</docTime>
<domTime>0</domTime>
<score_cache>42</score_cache>
<score_cdn>86</score_cdn>
<score_gzip>100</score_gzip>
<score_cookies>-1</score_cookies>
<score_keep-alive>98</score_keep-alive>
<score_minify>-1</score_minify>
<score_combine>100</score_combine>
<score_compress>-1</score_compress>
<score_etags>-1</score_etags>
<gzip_total>44767</gzip_total>
<gzip_savings>0</gzip_savings>
<minify_total>0</minify_total>
<minify_savings>0</minify_savings>
<image_total>0</image_total>
<image_savings>0</image_savings>
<optimization_checked>1</optimization_checked>
<aft>0</aft>
<domElements>1266</domElements>
<pageSpeedVersion>1.9</pageSpeedVersion>
<title>Colonial-style Alexandria mansion with four ovens lists for $2.095 million - The Washington Post</title>
<titleTime>1685</titleTime>
<loadEventStart>32773</loadEventStart>
<loadEventEnd>32785</loadEventEnd>
<domContentLoadedEventStart>9822</domContentLoadedEventStart>
<domContentLoadedEventEnd>9877</domContentLoadedEventEnd>
<lastVisualChange>33421</lastVisualChange>
<browser_name>Google Chrome</browser_name>
<browser_version>56.0.2924.87</browser_version>
<server_count>1</server_count>
<server_rtt>0</server_rtt>
<base_page_cdn>Instart Logic</base_page_cdn>
<adult_site>0</adult_site>
<fixed_viewport>1</fixed_viewport>
<score_progressive_jpeg>-1</score_progressive_jpeg>
<firstPaint>7061</firstPaint>
<docCPUms>19203.723</docCPUms>
<fullyLoadedCPUms>20966.534</fullyLoadedCPUms>
<docCPUpct>58</docCPUpct>
<fullyLoadedCPUpct>53</fullyLoadedCPUpct>
<isResponsive>-1</isResponsive>
<date>1487585104</date>
<CSI>
<value>v</value>
<value>s</value>
<value>action</value>
<value>it</value>
<value>srt</value>
<value>tbsrt</value>
<value>tran</value>
<value>p</value>
<value>npn</value>
<value>npnv</value>
<value>vrg</value>
<value>pl_id</value>
<value>e</value>
<value>rt</value>
<value>ad_render_period</value>
<value/>
</CSI>
<CSI.v>3</CSI.v>
<CSI.s>gpt</CSI.s>
<CSI.action>ad_events</CSI.action>
<CSI.it>ad_render_period.1.7342</CSI.it>
<CSI.srt>1567</CSI.srt>
<CSI.tbsrt>23628</CSI.tbsrt>
<CSI.tran>15</CSI.tran>
<CSI.p>s</CSI.p>
<CSI.npn>1</CSI.npn>
<CSI.npnv>h2</CSI.npnv>
<CSI.vrg>108</CSI.vrg>
<CSI.pl_id>1487585128403_0.6525457268218471</CSI.pl_id>
<CSI.e>v108,publisher_ads,n701,non-sra,fif,page_load,108809080,21060062,21060064</CSI.e>
<CSI.rt/>
<CSI.ad_render_period>1</CSI.ad_render_period>
<CSI./>
<SpeedIndex>6942</SpeedIndex>
<visualComplete>17200</visualComplete>
<chromeUserTiming>
<value>
<name>fetchStart</name>
<time>0</time>
</value>
<value>
<name>unloadEventStart</name>
<time>1570</time>
</value>
<value>
<name>unloadEventEnd</name>
<time>1570</time>
</value>
<value>
<name>responseEnd</name>
<time>1641</time>
</value>
<value>
<name>loadEventStart</name>
<time>32772</time>
</value>
<value>
<name>loadEventEnd</name>
<time>32785</time>
</value>
<value>
<name>firstMeaningfulPaint</name>
<time>7060</time>
</value>
</chromeUserTiming>
<chromeUserTiming.fetchStart>0</chromeUserTiming.fetchStart>
<chromeUserTiming.unloadEventStart>1570</chromeUserTiming.unloadEventStart>
<chromeUserTiming.unloadEventEnd>1570</chromeUserTiming.unloadEventEnd>
<chromeUserTiming.responseEnd>1641</chromeUserTiming.responseEnd>
<chromeUserTiming.loadEventStart>32772</chromeUserTiming.loadEventStart>
<chromeUserTiming.loadEventEnd>32785</chromeUserTiming.loadEventEnd>
<chromeUserTiming.firstMeaningfulPaint>7060</chromeUserTiming.firstMeaningfulPaint>
<run>1</run>
<effectiveBps>86290</effectiveBps>
<effectiveBpsDoc>90846</effectiveBpsDoc>
<consoleLog>
<entry>
<source>console-api</source>
<level>debug</level>
<message> [  0.004s] [studio.sdk] </message>
<url>https://s0.2mdn.net/ads/studio/Enabler.js</url>
<line>119</line>
</entry>
<entry>
<source>console-api</source>
<level>debug</level>
<message> [  1.032s] [studio.sdk] Using default ad parameters in test environment. Simulating local events.</message>
<url>https://s0.2mdn.net/ads/studio/Enabler.js</url>
<line>119</line>
</entry>
<entry>
<source>console-api</source>
<level>log</level>
<message>boomerang.nt: [info] This user agent supports NavigationTiming.</message>
<url>https://js.washingtonpost.com/wp-stat/rum/wprum.min.js</url>
<line>1</line>
</entry>
<entry>
<source>console-api</source>
<level>log</level>
<message>pt.fetchStart: 1487585104775</message>
<url>https://js.washingtonpost.com/wp-stat/rum/wprum.min.js</url>
<line>1</line>
</entry>
<entry>
<source>console-api</source>
<level>log</level>
<message>boomerang: [debug] Checking if we can send beacon</message>
<url>https://js.washingtonpost.com/wp-stat/rum/wprum.min.js</url>
<line>1</line>
</entry>
<entry>
<source>console-api</source>
<level>log</level>
<message>boomerang: [debug] Sending url: //rumds.wpdigital.net/metrics/?rum=%7B%22redt%22%3A0%2C%22nl%22%3A1640%2C%22dns%22%3A0%2C%22tcp%22%3A177%2C%22rest%22%3A503%2C%22domt%22%3A9876%2C%22uplt%22%3A32784%2C%22url%22%3A%22https%3A%2F%2Fwww.washingtonpost.com%2Fnews%2Fwhere-we-live%2Fwp%2F2017%2F02%2F09%2Fcolonial-style-alexandria-mansion-with-four-ovens-lists-for-2-095-million%2F%22%2C%22site%22%3A%22www.washingtonpost.com%22%2C%22title%22%3A%22Colonial-style%20Alexandria%20mansion%20with%20four%20ovens%20lists%20for%20%242.095%20million%20-%20The%20Washington%20Post%22%2C%22domn%22%3A1267%2C%22jhs%22%3A15200000%2C%22fpt%22%3A1487585111.835%2C%22section%22%3A%22realestate%22%2C%22cntt%22%3A%22blog%22%7Dv=0.9u=https%3A%2F%2Fwww.washingtonpost.com%2Fnews%2Fwhere-we-live%2Fwp%2F2017%2F02%2F09%2Fcolonial-style-alexandria-mansion-with-four-ovens-lists-for-2-095-million%2Fif=</message>
<url>https://js.washingtonpost.com/wp-stat/rum/wprum.min.js</url>
<line>1</line>
</entry>
<entry>
<source>console-api</source>
<level>debug</level>
<message>a: 0.035ms</message>
<url>https://cdn.adsafeprotected.com/sca.17.1.10.js</url>
<line>19</line>
</entry>
</consoleLog>
</firstView>
</median>
<run>
<id>1</id>
<firstView>
<tester>WIN-V9F8885QKK2-98.220.232.152</tester>
<results>
<URL>https://www.washingtonpost.com/news/where-we-live/wp/2017/02/09/colonial-style-alexandria-mansion-with-four-ovens-lists-for-2-095-million/</URL>
<loadTime>32794</loadTime>
<TTFB>606</TTFB>
<bytesOut>208119</bytesOut>
<bytesOutDoc>192845</bytesOutDoc>
<bytesIn>3016976</bytesIn>
<bytesInDoc>2924156</bytesInDoc>
<connections>99</connections>
<requests>239</requests>
<requestsFull>239</requestsFull>
<requestsDoc>233</requestsDoc>
<responses_200>155</responses_200>
<responses_404>0</responses_404>
<responses_other>54</responses_other>
<result>0</result>
<render>433</render>
<fullyLoaded>35569</fullyLoaded>
<cached>0</cached>
<docTime>32794</docTime>
<domTime>0</domTime>
<score_cache>42</score_cache>
<score_cdn>86</score_cdn>
<score_gzip>100</score_gzip>
<score_cookies>-1</score_cookies>
<score_keep-alive>98</score_keep-alive>
<score_minify>-1</score_minify>
<score_combine>100</score_combine>
<score_compress>-1</score_compress>
<score_etags>-1</score_etags>
<gzip_total>44767</gzip_total>
<gzip_savings>0</gzip_savings>
<minify_total>0</minify_total>
<minify_savings>0</minify_savings>
<image_total>0</image_total>
<image_savings>0</image_savings>
<optimization_checked>1</optimization_checked>
<aft>0</aft>
<domElements>1266</domElements>
<pageSpeedVersion>1.9</pageSpeedVersion>
<title>Colonial-style Alexandria mansion with four ovens lists for $2.095 million - The Washington Post</title>
<titleTime>1685</titleTime>
<loadEventStart>32773</loadEventStart>
<loadEventEnd>32785</loadEventEnd>
<domContentLoadedEventStart>9822</domContentLoadedEventStart>
<domContentLoadedEventEnd>9877</domContentLoadedEventEnd>
<lastVisualChange>33421</lastVisualChange>
<browser_name>Google Chrome</browser_name>
<browser_version>56.0.2924.87</browser_version>
<server_count>1</server_count>
<server_rtt>0</server_rtt>
<base_page_cdn>Instart Logic</base_page_cdn>
<adult_site>0</adult_site>
<fixed_viewport>1</fixed_viewport>
<score_progressive_jpeg>-1</score_progressive_jpeg>
<firstPaint>7061</firstPaint>
<docCPUms>19203.723</docCPUms>
<fullyLoadedCPUms>20966.534</fullyLoadedCPUms>
<docCPUpct>58</docCPUpct>
<fullyLoadedCPUpct>53</fullyLoadedCPUpct>
<isResponsive>-1</isResponsive>
<date>1487585104</date>
<CSI>
<value>v</value>
<value>s</value>
<value>action</value>
<value>it</value>
<value>srt</value>
<value>tbsrt</value>
<value>tran</value>
<value>p</value>
<value>npn</value>
<value>npnv</value>
<value>vrg</value>
<value>pl_id</value>
<value>e</value>
<value>rt</value>
<value>ad_render_period</value>
<value/>
</CSI>
<CSI.v>3</CSI.v>
<CSI.s>gpt</CSI.s>
<CSI.action>ad_events</CSI.action>
<CSI.it>ad_render_period.1.7342</CSI.it>
<CSI.srt>1567</CSI.srt>
<CSI.tbsrt>23628</CSI.tbsrt>
<CSI.tran>15</CSI.tran>
<CSI.p>s</CSI.p>
<CSI.npn>1</CSI.npn>
<CSI.npnv>h2</CSI.npnv>
<CSI.vrg>108</CSI.vrg>
<CSI.pl_id>1487585128403_0.6525457268218471</CSI.pl_id>
<CSI.e>v108,publisher_ads,n701,non-sra,fif,page_load,108809080,21060062,21060064</CSI.e>
<CSI.rt/>
<CSI.ad_render_period>1</CSI.ad_render_period>
<CSI./>
<SpeedIndex>6942</SpeedIndex>
<visualComplete>17200</visualComplete>
<chromeUserTiming>
<value>
<name>fetchStart</name>
<time>0</time>
</value>
<value>
<name>unloadEventStart</name>
<time>1570</time>
</value>
<value>
<name>unloadEventEnd</name>
<time>1570</time>
</value>
<value>
<name>responseEnd</name>
<time>1641</time>
</value>
<value>
<name>loadEventStart</name>
<time>32772</time>
</value>
<value>
<name>loadEventEnd</name>
<time>32785</time>
</value>
<value>
<name>firstMeaningfulPaint</name>
<time>7060</time>
</value>
</chromeUserTiming>
<chromeUserTiming.fetchStart>0</chromeUserTiming.fetchStart>
<chromeUserTiming.unloadEventStart>1570</chromeUserTiming.unloadEventStart>
<chromeUserTiming.unloadEventEnd>1570</chromeUserTiming.unloadEventEnd>
<chromeUserTiming.responseEnd>1641</chromeUserTiming.responseEnd>
<chromeUserTiming.loadEventStart>32772</chromeUserTiming.loadEventStart>
<chromeUserTiming.loadEventEnd>32785</chromeUserTiming.loadEventEnd>
<chromeUserTiming.firstMeaningfulPaint>7060</chromeUserTiming.firstMeaningfulPaint>
<run>1</run>
<effectiveBps>86290</effectiveBps>
<effectiveBpsDoc>90846</effectiveBpsDoc>
</results>
<pages>
<details>http://104.198.155.24/details.php?test=170220_MB_402967d9c046a02313f44041baa286b8&amp;run=1</details>
<checklist>http://104.198.155.24/performance_optimization.php?test=170220_MB_402967d9c046a02313f44041baa286b8&amp;run=1</checklist>
<breakdown>http://104.198.155.24/breakdown.php?test=170220_MB_402967d9c046a02313f44041baa286b8&amp;run=1</breakdown>
<domains>http://104.198.155.24/domains.php?test=170220_MB_402967d9c046a02313f44041baa286b8&amp;run=1</domains>
<screenShot>http://104.198.155.24/screen_shot.php?test=170220_MB_402967d9c046a02313f44041baa286b8&amp;run=1</screenShot>
</pages>
<thumbnails>
<waterfall>http://104.198.155.24/result/170220_MB_402967d9c046a02313f44041baa286b8/1_waterfall_thumb.png</waterfall>
<checklist>http://104.198.155.24/result/170220_MB_402967d9c046a02313f44041baa286b8/1_optimization_thumb.png</checklist>
<screenShot>http://104.198.155.24/result/170220_MB_402967d9c046a02313f44041baa286b8/1_screen_thumb.jpg</screenShot>
</thumbnails>
<images>
<waterfall>http://104.198.155.24/results/17/02/20/MB/402967d9c046a02313f44041baa286b8/1_waterfall.png</waterfall>
<connectionView>http://104.198.155.24/results/17/02/20/MB/402967d9c046a02313f44041baa286b8/1_connection.png</connectionView>
<checklist>http://104.198.155.24/results/17/02/20/MB/402967d9c046a02313f44041baa286b8/1_optimization.png</checklist>
<screenShot>http://104.198.155.24/getfile.php?test=170220_MB_402967d9c046a02313f44041baa286b8&amp;file=1_screen.jpg</screenShot>
</images>
<rawData><headers>http://104.198.155.24/results/17/02/20/MB/402967d9c046a02313f44041baa286b8/1_report.txt</headers>
<pageData>http://104.198.155.24/results/17/02/20/MB/402967d9c046a02313f44041baa286b8/1_IEWPG.txt</pageData>
<requestsData>http://104.198.155.24/results/17/02/20/MB/402967d9c046a02313f44041baa286b8/1_IEWTR.txt</requestsData>
<utilization>http://104.198.155.24/results/17/02/20/MB/402967d9c046a02313f44041baa286b8/1_progress.csv</utilization>
</rawData>
<videoFrames>
<frame>
<time>0</time>
<image>http://104.198.155.24/getfile.php?test=170220_MB_402967d9c046a02313f44041baa286b8&amp;video=video_1&amp;file=frame_0000.jpg</image>
<VisuallyComplete>0</VisuallyComplete>
</frame>
<frame>
<time>400</time>
<image>http://104.198.155.24/getfile.php?test=170220_MB_402967d9c046a02313f44041baa286b8&amp;video=video_1&amp;file=frame_0004.jpg</image>
<VisuallyComplete>1</VisuallyComplete>
</frame>
<frame>
<time>600</time>
<image>http://104.198.155.24/getfile.php?test=170220_MB_402967d9c046a02313f44041baa286b8&amp;video=video_1&amp;file=frame_0006.jpg</image>
<VisuallyComplete>35</VisuallyComplete>
</frame>
<frame>
<time>700</time>
<image>http://104.198.155.24/getfile.php?test=170220_MB_402967d9c046a02313f44041baa286b8&amp;video=video_1&amp;file=frame_0007.jpg</image>
<VisuallyComplete>35</VisuallyComplete>
</frame>
<frame>
<time>2500</time>
<image>http://104.198.155.24/getfile.php?test=170220_MB_402967d9c046a02313f44041baa286b8&amp;video=video_1&amp;file=frame_0025.jpg</image>
<VisuallyComplete>35</VisuallyComplete>
</frame>
<frame>
<time>2700</time>
<image>http://104.198.155.24/getfile.php?test=170220_MB_402967d9c046a02313f44041baa286b8&amp;video=video_1&amp;file=frame_0027.jpg</image>
<VisuallyComplete>33</VisuallyComplete>
</frame>
<frame>
<time>7300</time>
<image>http://104.198.155.24/getfile.php?test=170220_MB_402967d9c046a02313f44041baa286b8&amp;video=video_1&amp;file=frame_0073.jpg</image>
<VisuallyComplete>60</VisuallyComplete>
</frame>
<frame>
<time>7500</time>
<image>http://104.198.155.24/getfile.php?test=170220_MB_402967d9c046a02313f44041baa286b8&amp;video=video_1&amp;file=frame_0075.jpg</image>
<VisuallyComplete>60</VisuallyComplete>
</frame>
<frame>
<time>7900</time>
<image>http://104.198.155.24/getfile.php?test=170220_MB_402967d9c046a02313f44041baa286b8&amp;video=video_1&amp;file=frame_0079.jpg</image>
<VisuallyComplete>60</VisuallyComplete>
</frame>
<frame>
<time>9900</time>
<image>http://104.198.155.24/getfile.php?test=170220_MB_402967d9c046a02313f44041baa286b8&amp;video=video_1&amp;file=frame_0099.jpg</image>
<VisuallyComplete>62</VisuallyComplete>
</frame>
<frame>
<time>10600</time>
<image>http://104.198.155.24/getfile.php?test=170220_MB_402967d9c046a02313f44041baa286b8&amp;video=video_1&amp;file=frame_0106.jpg</image>
<VisuallyComplete>62</VisuallyComplete>
</frame>
<frame>
<time>10800</time>
<image>http://104.198.155.24/getfile.php?test=170220_MB_402967d9c046a02313f44041baa286b8&amp;video=video_1&amp;file=frame_0108.jpg</image>
<VisuallyComplete>61</VisuallyComplete>
</frame>
<frame>
<time>11500</time>
<image>http://104.198.155.24/getfile.php?test=170220_MB_402967d9c046a02313f44041baa286b8&amp;video=video_1&amp;file=frame_0115.jpg</image>
<VisuallyComplete>62</VisuallyComplete>
</frame>
<frame>
<time>12000</time>
<image>http://104.198.155.24/getfile.php?test=170220_MB_402967d9c046a02313f44041baa286b8&amp;video=video_1&amp;file=frame_0120.jpg</image>
<VisuallyComplete>99</VisuallyComplete>
</frame>
<frame>
<time>12100</time>
<image>http://104.198.155.24/getfile.php?test=170220_MB_402967d9c046a02313f44041baa286b8&amp;video=video_1&amp;file=frame_0121.jpg</image>
<VisuallyComplete>99</VisuallyComplete>
</frame>
<frame>
<time>12300</time>
<image>http://104.198.155.24/getfile.php?test=170220_MB_402967d9c046a02313f44041baa286b8&amp;video=video_1&amp;file=frame_0123.jpg</image>
<VisuallyComplete>99</VisuallyComplete>
</frame>
<frame>
<time>12700</time>
<image>http://104.198.155.24/getfile.php?test=170220_MB_402967d9c046a02313f44041baa286b8&amp;video=video_1&amp;file=frame_0127.jpg</image>
<VisuallyComplete>99</VisuallyComplete>
</frame>
<frame>
<time>13500</time>
<image>http://104.198.155.24/getfile.php?test=170220_MB_402967d9c046a02313f44041baa286b8&amp;video=video_1&amp;file=frame_0135.jpg</image>
<VisuallyComplete>99</VisuallyComplete>
</frame>
<frame>
<time>13700</time>
<image>http://104.198.155.24/getfile.php?test=170220_MB_402967d9c046a02313f44041baa286b8&amp;video=video_1&amp;file=frame_0137.jpg</image>
<VisuallyComplete>99</VisuallyComplete>
</frame>
<frame>
<time>17200</time>
<image>http://104.198.155.24/getfile.php?test=170220_MB_402967d9c046a02313f44041baa286b8&amp;video=video_1&amp;file=frame_0172.jpg</image>
<VisuallyComplete>100</VisuallyComplete>
</frame>
<frame>
<time>24800</time>
<image>http://104.198.155.24/getfile.php?test=170220_MB_402967d9c046a02313f44041baa286b8&amp;video=video_1&amp;file=frame_0248.jpg</image>
<VisuallyComplete>100</VisuallyComplete>
</frame>
<frame>
<time>26300</time>
<image>http://104.198.155.24/getfile.php?test=170220_MB_402967d9c046a02313f44041baa286b8&amp;video=video_1&amp;file=frame_0263.jpg</image>
<VisuallyComplete>100</VisuallyComplete>
</frame>
<frame>
<time>26500</time>
<image>http://104.198.155.24/getfile.php?test=170220_MB_402967d9c046a02313f44041baa286b8&amp;video=video_1&amp;file=frame_0265.jpg</image>
<VisuallyComplete>100</VisuallyComplete>
</frame>
<frame>
<time>26800</time>
<image>http://104.198.155.24/getfile.php?test=170220_MB_402967d9c046a02313f44041baa286b8&amp;video=video_1&amp;file=frame_0268.jpg</image>
<VisuallyComplete>100</VisuallyComplete>
</frame>
<frame>
<time>27300</time>
<image>http://104.198.155.24/getfile.php?test=170220_MB_402967d9c046a02313f44041baa286b8&amp;video=video_1&amp;file=frame_0273.jpg</image>
<VisuallyComplete>100</VisuallyComplete>
</frame>
<frame>
<time>27400</time>
<image>http://104.198.155.24/getfile.php?test=170220_MB_402967d9c046a02313f44041baa286b8&amp;video=video_1&amp;file=frame_0274.jpg</image>
<VisuallyComplete>100</VisuallyComplete>
</frame>
<frame>
<time>27600</time>
<image>http://104.198.155.24/getfile.php?test=170220_MB_402967d9c046a02313f44041baa286b8&amp;video=video_1&amp;file=frame_0276.jpg</image>
<VisuallyComplete>100</VisuallyComplete>
</frame>
<frame>
<time>31100</time>
<image>http://104.198.155.24/getfile.php?test=170220_MB_402967d9c046a02313f44041baa286b8&amp;video=video_1&amp;file=frame_0311.jpg</image>
<VisuallyComplete>100</VisuallyComplete>
</frame>
<frame>
<time>32200</time>
<image>http://104.198.155.24/getfile.php?test=170220_MB_402967d9c046a02313f44041baa286b8&amp;video=video_1&amp;file=frame_0322.jpg</image>
<VisuallyComplete>100</VisuallyComplete>
</frame>
<frame>
<time>32800</time>
<image>http://104.198.155.24/getfile.php?test=170220_MB_402967d9c046a02313f44041baa286b8&amp;video=video_1&amp;file=frame_0328.jpg</image>
<VisuallyComplete>100</VisuallyComplete>
</frame>
<frame>
<time>33400</time>
<image>http://104.198.155.24/getfile.php?test=170220_MB_402967d9c046a02313f44041baa286b8&amp;video=video_1&amp;file=frame_0334.jpg</image>
<VisuallyComplete>100</VisuallyComplete>
</frame>
</videoFrames>
<consoleLog>
<entry>
<source>console-api</source>
<level>debug</level>
<message> [  0.004s] [studio.sdk] </message>
<url>https://s0.2mdn.net/ads/studio/Enabler.js</url>
<line>119</line>
</entry>
<entry>
<source>console-api</source>
<level>debug</level>
<message> [  1.032s] [studio.sdk] Using default ad parameters in test environment. Simulating local events.</message>
<url>https://s0.2mdn.net/ads/studio/Enabler.js</url>
<line>119</line>
</entry>
<entry>
<source>console-api</source>
<level>log</level>
<message>boomerang.nt: [info] This user agent supports NavigationTiming.</message>
<url>https://js.washingtonpost.com/wp-stat/rum/wprum.min.js</url>
<line>1</line>
</entry>
<entry>
<source>console-api</source>
<level>log</level>
<message>pt.fetchStart: 1487585104775</message>
<url>https://js.washingtonpost.com/wp-stat/rum/wprum.min.js</url>
<line>1</line>
</entry>
<entry>
<source>console-api</source>
<level>log</level>
<message>boomerang: [debug] Checking if we can send beacon</message>
<url>https://js.washingtonpost.com/wp-stat/rum/wprum.min.js</url>
<line>1</line>
</entry>
<entry>
<source>console-api</source>
<level>log</level>
<message>boomerang: [debug] Sending url: //rumds.wpdigital.net/metrics/?rum=%7B%22redt%22%3A0%2C%22nl%22%3A1640%2C%22dns%22%3A0%2C%22tcp%22%3A177%2C%22rest%22%3A503%2C%22domt%22%3A9876%2C%22uplt%22%3A32784%2C%22url%22%3A%22https%3A%2F%2Fwww.washingtonpost.com%2Fnews%2Fwhere-we-live%2Fwp%2F2017%2F02%2F09%2Fcolonial-style-alexandria-mansion-with-four-ovens-lists-for-2-095-million%2F%22%2C%22site%22%3A%22www.washingtonpost.com%22%2C%22title%22%3A%22Colonial-style%20Alexandria%20mansion%20with%20four%20ovens%20lists%20for%20%242.095%20million%20-%20The%20Washington%20Post%22%2C%22domn%22%3A1267%2C%22jhs%22%3A15200000%2C%22fpt%22%3A1487585111.835%2C%22section%22%3A%22realestate%22%2C%22cntt%22%3A%22blog%22%7Dv=0.9u=https%3A%2F%2Fwww.washingtonpost.com%2Fnews%2Fwhere-we-live%2Fwp%2F2017%2F02%2F09%2Fcolonial-style-alexandria-mansion-with-four-ovens-lists-for-2-095-million%2Fif=</message>
<url>https://js.washingtonpost.com/wp-stat/rum/wprum.min.js</url>
<line>1</line>
</entry>
<entry>
<source>console-api</source>
<level>debug</level>
<message>a: 0.035ms</message>
<url>https://cdn.adsafeprotected.com/sca.17.1.10.js</url>
<line>19</line>
</entry>
</consoleLog>
</firstView>
</run>
</data>
</response>